{
    "0": "ID",
    "161404": "BT",
    "161405": "ID",
    "1048576": "JP",
    "1507328": "NZ",
    "1572864": "TW",
    "1835008": "CN",
    "1892352": "HK",
    "1893632": "CN",
    "1900544": "KR",
    "1949696": "AU",
    "1949952": "SG",
    "1950080": "JP",
    "1950112": "SG",
    "1952256": "AU",
    "1952272": "SG",
    "1952288": "AU",
    "1952320": "SG",
    "1952360": "AU",
    "1952768": "SG",
    "1953536": "JP",
    "1953792": "SG",
    "1954240": "JP",
    "1954304": "SG",
    "1955328": "JP",
    "1955584": "SG",
    "1955840": "JP",
    "1956000": "SG",
    "1956016": "JP",
    "1956352": "SG",
    "1956480": "JP",
    "1956520": "SG",
    "1956528": "JP",
    "1956536": "SG",
    "1956544": "JP",
    "1956608": "SG",
    "1956736": "JP",
    "1956776": "SG",
    "1956784": "JP",
    "1956792": "SG",
    "1956800": "JP",
    "1956832": "SG",
    "1956896": "JP",
    "1956904": "IN",
    "1956912": "JP",
    "1956920": "SG",
    "1956928": "JP",
    "1956992": "IN",
    "1957000": "SG",
    "1957008": "AU",
    "1957112": "JP",
    "1957168": "SG",
    "1957192": "JP",
    "1957208": "SG",
    "1957240": "AU",
    "1957248": "JP",
    "1957256": "SG",
    "1957272": "JP",
    "1957280": "SG",
    "1957376": "JP",
    "1957632": "KR",
    "1957640": "SG",
    "1957648": "AU",
    "1957656": "JP",
    "1957664": "KR",
    "1957672": "SG",
    "1957696": "JP",
    "1957712": "SG",
    "1957760": "JP",
    "1957768": "SG",
    "1957808": "KR",
    "1957816": "SG",
    "1957888": "IN",
    "1960960": "HK",
    "1961984": "TW",
    "1964032": "IN",
    "1965056": "HK",
    "1966080": "KR",
    "1974272": "TW",
    "1978368": "KR",
    "1982464": "AU",
    "1984512": "IN",
    "1986560": "ID",
    "1990656": "AU",
    "1998848": "KR",
    "2031616": "BD",
    "2039808": "KR",
    "2048000": "CN",
    "2050048": "AU",
    "2052096": "JP",
    "2056192": "AU",
    "2058240": "JP",
    "2060288": "KR",
    "2064384": "IN",
    "2080768": "AU",
    "2082560": "US",
    "2082816": "AU",
    "2083328": "NZ",
    "2083840": "AU",
    "2084864": "NZ",
    "2086912": "JP",
    "2088960": "IN",
    "2093056": "ID",
    "2095104": "IN",
    "2097152": "TW",
    "3145728": "JP",
    "3407872": "KR",
    "3538944": "CN",
    "3670016": "US",
    "3932160": "CN",
    "4521984": "JP",
    "4567040": "NC",
    "4579328": "IN",
    "4580096": "DE",
    "4580352": "IN",
    "4583680": "EE",
    "4583936": "IN",
    "4584448": "KR",
    "4584704": "HR",
    "4584960": "US",
    "4585216": "KR",
    "4585472": "IN",
    "4585984": "US",
    "4586496": "IN",
    "4587520": "KR",
    "4718592": "AU",
    "5177344": "ID",
    "5193728": "CN",
    "5210112": "IN",
    "5242880": "CN",
    "7077888": "KR",
    "7127040": "PH",
    "7143424": "TH",
    "7208960": "CN",
    "7213056": "ID",
    "7215104": "KR",
    "7217152": "NZ",
    "7219200": "ID",
    "7221248": "JP",
    "7225344": "CN",
    "7241728": "KR",
    "7274496": "CN",
    "7282688": "KR",
    "7288832": "US",
    "7289088": "KR",
    "7290880": "JP",
    "7307264": "AU",
    "7315456": "CN",
    "7323648": "KR",
    "7340032": "HK",
    "7405568": "CN",
    "7831552": "SG",
    "7847936": "CN",
    "7864320": "ID",
    "8388608": "TH",
    "8454144": "JP",
    "8456192": "GB",
    "8456704": "BD",
    "8458240": "ID",
    "8460288": "LA",
    "8462336": "SG",
    "8464896": "AU",
    "8465152": "NZ",
    "8465408": "AE",
    "8465664": "SG",
    "8466432": "JP",
    "8470528": "KR",
    "8486912": "US",
    "8488609": "AU",
    "8488610": "US",
    "8490134": "AU",
    "8490135": "US",
    "8490616": "AU",
    "8490617": "US",
    "8492179": "AU",
    "8492180": "US",
    "8495104": "AU",
    "8503296": "KR",
    "8519680": "BD",
    "8585216": "TH",
    "8650752": "CN",
    "8716288": "MY",
    "8781824": "NZ",
    "8785920": "IN",
    "8788992": "JP",
    "8798208": "ID",
    "8802304": "HK",
    "8804352": "BD",
    "8806400": "JP",
    "8822784": "NZ",
    "8828928": "HK",
    "8829952": "CN",
    "8830464": "KH",
    "8830976": "JP",
    "8847360": "CN",
    "8912896": "TW",
    "9043968": "CN",
    "9175040": "TW",
    "9240576": "KR",
    "9248768": "JP",
    "9250816": "KR",
    "9252864": "ID",
    "9256960": "CN",
    "9259008": "SG",
    "9261056": "CN",
    "9263104": "ID",
    "9265152": "AU",
    "9269248": "PF",
    "9271296": "JP",
    "9273344": "CN",
    "9289728": "AU",
    "9290240": "NZ",
    "9290496": "AU",
    "9293824": "SG",
    "9295872": "PH",
    "9297920": "KR",
    "9306112": "JP",
    "9340928": "IN",
    "9341184": "CN",
    "9341440": "IN",
    "9341456": "CN",
    "9342208": "IN",
    "9342976": "HK",
    "9347072": "AU",
    "9348096": "IN",
    "9349120": "ID",
    "9351168": "JP",
    "9355264": "GU",
    "9371648": "IN",
    "9437184": "JP",
    "12845056": "CN",
    "12976128": "AU",
    "13008896": "PH",
    "13017088": "TW",
    "13025280": "JP",
    "13035520": "PK",
    "13036538": "EG",
    "13036539": "PK",
    "13037568": "ID",
    "13039616": "CN",
    "13041664": "KR",
    "13058048": "HK",
    "13062144": "ID",
    "13074432": "KR",
    "13631488": "CN"
}