{
    "0": "US",
    "196608": "JP",
    "204800": "US",
    "253952": "BG",
    "258048": "US",
    "786432": "CA",
    "851968": "US",
    "1649856": "GB",
    "1649888": "US",
    "1649920": "GB",
    "1650176": "US",
    "1654840": "CA",
    "1654848": "US",
    "1655808": "CA",
    "1656576": "US",
    "1656832": "CA",
    "1658880": "US",
    "1880064": "CA",
    "1881088": "US",
    "1933312": "CA",
    "1937408": "US",
    "2126848": "CA",
    "2127872": "US",
    "2687796": "AU",
    "2687800": "US",
    "2703104": "GB",
    "2703360": "US",
    "2705408": "GB",
    "2705664": "US",
    "2705920": "GB",
    "2707456": "CA",
    "2711552": "US",
    "2713600": "CA",
    "2713856": "US",
    "2714112": "NL",
    "2714368": "JM",
    "2714624": "US",
    "2715392": "CA",
    "2715648": "US",
    "2728960": "CA",
    "2729216": "US",
    "2729984": "CA",
    "2730496": "US",
    "2730752": "CA",
    "2733056": "US",
    "2733825": "CA",
    "2735104": "US",
    "2735872": "ES",
    "2736128": "US",
    "2949120": "CA",
    "3014656": "US",
    "3080192": "CA",
    "3124480": "US",
    "3124736": "CA",
    "3145728": "US",
    "3159296": "VE",
    "3160064": "AG",
    "3160576": "US",
    "3161600": "AG",
    "3162112": "US",
    "3204096": "KY",
    "3204352": "US",
    "3221504": "CL",
    "3222528": "VE",
    "3223552": "US",
    "3229440": "VE",
    "3229696": "US",
    "3236864": "CA",
    "3237120": "US",
    "3256320": "CO",
    "3258368": "AR",
    "3260416": "VE",
    "3262464": "US",
    "3264512": "PE",
    "3266560": "CL",
    "3268608": "US",
    "3342336": "PR",
    "3342592": "CA",
    "3344128": "US",
    "3344384": "CA",
    "3350016": "US",
    "3350272": "CA",
    "3350784": "US",
    "3351040": "CA",
    "3351296": "US",
    "3405824": "CA",
    "3407360": "US",
    "3485696": "CA",
    "3489792": "US",
    "3508736": "GB",
    "3508992": "US",
    "3509248": "CA",
    "3509504": "DM",
    "3509760": "US",
    "3510272": "CA",
    "3511296": "",
    "3511504": "ID",
    "3511505": "",
    "3511552": "CA",
    "3512320": "",
    "3512576": "CA",
    "3514368": "US",
    "3518464": "BM",
    "3522560": "US",
    "3581952": "NL",
    "3581984": "US",
    "3582720": "NL",
    "3582976": "US",
    "3624960": "CA",
    "3629056": "US",
    "3736064": "AR",
    "3736576": "US",
    "3741312": "JP",
    "3741376": "US",
    "3742464": "FR",
    "3742720": "US",
    "3766816": "MX",
    "3766832": "US",
    "4005476": "MX",
    "4005477": "PE",
    "4005478": "US",
    "4063232": "PS",
    "4071424": "US",
    "4071936": "NZ",
    "4072448": "US",
    "4073472": "LB",
    "4076544": "KZ",
    "4077568": "IN",
    "4079616": "BR",
    "4096000": "PS",
    "4104192": "VE",
    "4112384": "AM",
    "4120576": "CL",
    "4128768": "US",
    "4304654": "",
    "4304655": "US",
    "4655872": "CA",
    "4656128": "US",
    "4656896": "VG",
    "4657152": "US",
    "4688128": "CA",
    "4688384": "US",
    "4693856": "RU",
    "4693888": "US",
    "4693912": "NL",
    "4693920": "US",
    "4694528": "",
    "4694784": "US",
    "4771840": "CA",
    "4772096": "US",
    "4915200": "CA",
    "4980736": "US",
    "5180384": "GB",
    "5180416": "US",
    "5303552": "CA",
    "5303808": "US",
    "5304064": "CA",
    "5308416": "US",
    "5312512": "DE",
    "5316608": "US",
    "5335040": "CA",
    "5335296": "US",
    "5336576": "VG",
    "5336832": "US",
    "5354752": "DE",
    "5355008": "SG",
    "5355264": "US",
    "5355520": "AU",
    "5356032": "US",
    "5356288": "SG",
    "5356544": "US",
    "5402112": "CA",
    "5402624": "US",
    "5409280": "CA",
    "5409536": "US",
    "5442816": "AG",
    "5443072": "US",
    "5443328": "CA",
    "5443584": "US",
    "5449728": "NL",
    "5449984": "NO",
    "5450240": "US",
    "5451008": "BL",
    "5451264": "CA",
    "5451520": "VC",
    "5451776": "US",
    "5477376": "CA",
    "5477888": "US",
    "5505024": "CL",
    "5509120": "US",
    "5513216": "BR",
    "5521408": "PS",
    "5525504": "BA",
    "5526528": "US",
    "5529600": "ID",
    "5537792": "PK",
    "5554176": "US",
    "5555936": "IN",
    "5555937": "US",
    "5562368": "IN",
    "5566464": "US",
    "5570560": "RU",
    "5586944": "US",
    "5611520": "IN",
    "5612544": "BR",
    "5613568": "US",
    "5615616": "PK",
    "5619712": "US",
    "5701632": "CA",
    "5767168": "US",
    "6553600": "SG",
    "6555136": "US",
    "6910976": "HN",
    "6911232": "US",
    "7069952": "CW",
    "7070208": "US",
    "7077888": "CA",
    "7086080": "US",
    "7086336": "CA",
    "7088128": "US",
    "7092224": "CA",
    "7106816": "US",
    "7107328": "NL",
    "7107584": "US",
    "7108608": "CA",
    "7137280": "US",
    "7138560": "CA",
    "7143168": "US",
    "7602176": "CA",
    "7667712": "US",
    "7831552": "MO",
    "7839744": "US",
    "8021588": "",
    "8021589": "US",
    "8060928": "GB",
    "8061184": "CA",
    "8062720": "US",
    "8062976": "CA",
    "8065280": "US",
    "8065536": "CA",
    "8067072": "US",
    "8067328": "CA",
    "8068608": "GB",
    "8068864": "CA",
    "8074240": "US",
    "8094208": "AU",
    "8094464": "CZ",
    "8094720": "US",
    "8094976": "CA",
    "8095232": "DE",
    "8095488": "NL",
    "8095744": "CA",
    "8096000": "SE",
    "8096256": "SG",
    "8096512": "RU",
    "8096768": "DE",
    "8097024": "US",
    "8098304": "KW",
    "8098560": "NL",
    "8098816": "SE",
    "8099072": "FR",
    "8099328": "AF",
    "8099456": "UZ",
    "8099584": "TJ",
    "8099712": "KG",
    "8099840": "KZ",
    "8099968": "TM",
    "8100096": "LA",
    "8100224": "MN",
    "8100352": "LK",
    "8100480": "BD",
    "8100608": "MM",
    "8100736": "PG",
    "8100864": "TZ",
    "8100992": "MG",
    "8101120": "AO",
    "8101248": "NE",
    "8101376": "MR",
    "8101504": "SN",
    "8101632": "TN",
    "8101760": "DZ",
    "8101888": "CA",
    "8110080": "US",
    "8155136": "CA",
    "8159232": "US",
    "8233984": "CA",
    "8235008": "US",
    "8235792": "VN",
    "8235800": "US",
    "8243200": "CA",
    "8245248": "US",
    "8278016": "CA",
    "8282112": "US",
    "8285440": "CA",
    "8285696": "US",
    "8286208": "CA",
    "8286464": "US",
    "8288256": "LC",
    "8290304": "US",
    "8315136": "CA",
    "8315392": "US",
    "8320000": "GD",
    "8320256": "US",
    "8322816": "CA",
    "8323072": "US",
    "8372224": "SG",
    "8373248": "BR",
    "8374272": "JP",
    "8375296": "SG",
    "8376320": "AU",
    "8377344": "NL",
    "8377600": "SE",
    "8377856": "IL",
    "8378112": "FR",
    "8378368": "JP",
    "8378624": "PL",
    "8378880": "US",
    "8379392": "SG",
    "8380416": "US",
    "8519936": "CA",
    "8520192": "GB",
    "8520704": "US",
    "8521472": "CA",
    "8522240": "US",
    "8522496": "CA",
    "8523776": "US",
    "8524800": "CA",
    "8530688": "US",
    "8530944": "CA",
    "8532992": "US",
    "8533248": "CA",
    "8535296": "GB",
    "8535552": "US",
    "8536064": "CA",
    "8536320": "US",
    "8536576": "CA",
    "8541440": "US",
    "8541696": "CA",
    "8542208": "US",
    "8542720": "CA",
    "8543744": "US",
    "8557824": "CA",
    "8578048": "BL",
    "8578304": "CA",
    "8581888": "US",
    "8582144": "CA",
    "8585216": "US",
    "8634368": "HK",
    "8638464": "US",
    "8642560": "CA",
    "8650752": "US",
    "8663040": "CA",
    "8667136": "US",
    "8677376": "AR",
    "8679424": "US",
    "8708096": "PA",
    "8709120": "US",
    "8711376": "MX",
    "8711392": "US",
    "9048064": "BS",
    "9052160": "US",
    "9355264": "GB",
    "9363456": "US",
    "9363944": "GB",
    "9363948": "US",
    "9366016": "GB",
    "9366528": "US",
    "9699328": "AU",
    "9699584": "US",
    "9846784": "CA",
    "9854976": "US",
    "9961472": "CA",
    "9963520": "US",
    "9965312": "CA",
    "9966080": "US",
    "9966560": "CA",
    "9966592": "US",
    "9968448": "CA",
    "9968456": "US",
    "9969664": "CA",
    "9977856": "US",
    "10458249": "BH",
    "10458250": "US",
    "10610432": "HK",
    "10610448": "US",
    "10610950": "",
    "10610954": "US",
    "10649600": "CA",
    "10665984": "US",
    "10739712": "CA",
    "10747904": "US",
    "10819790": "FR",
    "10819791": "US",
    "10820056": "IT",
    "10820064": "US",
    "10822912": "IT",
    "10823168": "US",
    "10831168": "DE",
    "10831174": "",
    "10831175": "DE",
    "10831232": "US",
    "10832312": "GB",
    "10832316": "US",
    "10931200": "PR",
    "10932224": "US",
    "10943232": "NL",
    "10943488": "US",
    "10944512": "CA",
    "10944768": "US",
    "10945024": "CA",
    "10950144": "US",
    "10950400": "CA",
    "10952960": "OM",
    "10953216": "CA",
    "10956800": "US",
    "10957056": "CA",
    "10962432": "US",
    "10962944": "CA",
    "11010048": "US",
    "11272192": "CA",
    "11337728": "US",
    "11448320": "CA",
    "11460608": "US",
    "11567104": "CA",
    "11575296": "US",
    "11599872": "CA",
    "11796480": "US",
    "11857920": "CA",
    "11862016": "US",
    "12132352": "ZA",
    "12135424": "US",
    "12138496": "ZA",
    "12139520": "US",
    "12189696": "CA",
    "12255232": "US",
    "12337152": "CA",
    "12353536": "BM",
    "12361728": "US",
    "12386304": "NL",
    "12390400": "GB",
    "12394496": "SG",
    "12398592": "DE",
    "12402688": "US",
    "12406784": "SG",
    "12410880": "NL",
    "12414976": "GB",
    "12419072": "IN",
    "12423168": "SG",
    "12427264": "US",
    "12447744": "NL",
    "12448768": "GB",
    "12449792": "DE",
    "12450816": "US",
    "12491264": "SG",
    "12491896": "NL",
    "12491904": "SG",
    "12492544": "HK",
    "12492800": "US",
    "12507136": "PR",
    "12508160": "US",
    "12511232": "JP",
    "12513280": "US",
    "12517376": "CA",
    "12550144": "US",
    "12575696": "SG",
    "12575712": "US",
    "12575920": "SG",
    "12575952": "US",
    "12575984": "SG",
    "12576000": "US",
    "12576096": "SG",
    "12576112": "US",
    "12576160": "SG",
    "12576176": "US",
    "12576272": "HK",
    "12576288": "US",
    "12576336": "HK",
    "12576352": "US",
    "12576448": "HK",
    "12576464": "US",
    "12576512": "HK",
    "12576528": "US",
    "12578816": "IE",
    "12578832": "US",
    "12578848": "IE",
    "12579040": "US",
    "12579088": "IE",
    "12579168": "NL",
    "12579296": "US",
    "12579312": "NL",
    "12579344": "US",
    "12579488": "NL",
    "12579520": "US",
    "12580592": "NL",
    "12580768": "US",
    "12580960": "IE",
    "12581088": "US",
    "12581120": "IE",
    "12581136": "NL",
    "12581280": "US",
    "12581296": "NL",
    "12581312": "US",
    "12581328": "NL",
    "12581392": "US",
    "12581424": "NL",
    "12581440": "US",
    "12581536": "IE",
    "12581552": "US",
    "12581568": "IE",
    "12581584": "US",
    "12581600": "IE",
    "12581616": "US",
    "12581648": "IE",
    "12581664": "US",
    "12581888": "IE",
    "12581904": "NL",
    "12581936": "IE",
    "12581952": "US",
    "12582016": "IE",
    "12582032": "NL",
    "12582064": "IE",
    "12582080": "US",
    "12582336": "IE",
    "12582352": "NL",
    "12582384": "IE",
    "12582400": "US",
    "12582448": "IE",
    "12582464": "US",
    "12691968": "BE",
    "12692224": "US",
    "12692480": "BE",
    "12692736": "US",
    "12787712": "DE",
    "12795904": "US",
    "12849152": "CA",
    "12849664": "US",
    "12871424": "",
    "12871680": "US",
    "12918528": "CA",
    "12918755": "US",
    "12918756": "CA",
    "12918784": "US",
    "12925696": "",
    "12925952": "US",
    "12949248": "CA",
    "12949504": "US",
    "12957696": "",
    "12957952": "US",
    "12963840": "GB",
    "12964096": "US",
    "13023232": "CA",
    "13026304": "US",
    "13165568": "DE",
    "13166080": "US",
    "13172736": "PH",
    "13176832": "US",
    "13230080": "CA",
    "13232128": "US",
    "13516800": "CA",
    "13533184": "US",
    "13640704": "CA",
    "13641216": "US",
    "13693952": "CA",
    "13694976": "US",
    "13716480": "SG",
    "13716736": "IN",
    "13717248": "US",
    "13787136": "CA",
    "13795328": "US",
    "13883392": "CA",
    "13883904": "US",
    "14024704": "AG",
    "14032896": "US",
    "14082144": "CA",
    "14082176": "US",
    "14082400": "CA",
    "14082432": "US",
    "14083168": "CA",
    "14083200": "US",
    "14083424": "CA",
    "14083456": "US",
    "14083616": "CA",
    "14083648": "US",
    "14083680": "CA",
    "14083712": "US",
    "14083936": "CA",
    "14083968": "US",
    "14084192": "CA",
    "14084224": "US",
    "14084448": "CA",
    "14084480": "US",
    "14084672": "CA",
    "14084736": "US",
    "14084960": "CA",
    "14084992": "US",
    "14086144": "CA",
    "14090240": "US",
    "14276096": "GB",
    "14276352": "US",
    "14276608": "NL",
    "14276864": "US",
    "14277888": "GB",
    "14278144": "US",
    "14352384": "KR",
    "14368768": "US",
    "14402816": "CA",
    "14403072": "US",
    "14451712": "HK",
    "14452736": "US",
    "14466048": "CA",
    "14469120": "US",
    "14503936": "AR",
    "14508032": "US",
    "14544896": "CA",
    "14548992": "US",
    "14565376": "CA",
    "14573568": "US",
    "14637568": "CA",
    "14638080": "US",
    "14639360": "CA",
    "14639616": "US",
    "14643456": "CA",
    "14643968": "US",
    "14646272": "CO",
    "14646528": "US",
    "14647040": "CA",
    "14647296": "US",
    "14647552": "CA",
    "14647808": "PE",
    "14648064": "US",
    "14649344": "ZA",
    "14649600": "US",
    "14650112": "CA",
    "14650368": "US",
    "14655488": "CA",
    "14663680": "US",
    "14672896": "GB",
    "14673920": "AR",
    "14674944": "BE",
    "14675968": "CA",
    "14676992": "US",
    "14679040": "NL",
    "14679296": "GB",
    "14679552": "CA",
    "14679808": "GB",
    "14680064": "US",
    "14688256": "PA",
    "14696448": "US",
    "14778368": "HK",
    "14779392": "FR",
    "14780416": "US",
    "14987120": "SK",
    "14987121": "US",
    "15169536": "BB",
    "15171584": "US",
    "15176284": "TH",
    "15176285": "US",
    "15464448": "CA",
    "15466496": "US",
    "16142848": "CA",
    "16143104": "US",
    "16151104": "MX",
    "16151132": "RU",
    "16151133": "MX",
    "16151136": "MY",
    "16151168": "US",
    "16269312": "PR",
    "16285696": "CA",
    "16302080": "US",
    "16461824": "",
    "16465920": "US",
    "16572416": "PL",
    "16580608": "US",
    "16596992": "CA",
    "16601088": "US",
    "16603136": "CA",
    "16604160": "US",
    "16615424": "CA",
    "16617472": "US"
}