{
    "0": "DE",
    "495104": "CN",
    "495105": "DE",
    "524288": "GB",
    "532480": "TJ",
    "536576": "DE",
    "540672": "SA",
    "544768": "RU",
    "548864": "NL",
    "549888": "ES",
    "550144": "NL",
    "550400": "FR",
    "550656": "IE",
    "550912": "NL",
    "552960": "PL",
    "553984": "MX",
    "554240": "TM",
    "554496": "US",
    "554752": "GB",
    "555008": "TR",
    "556032": "RU",
    "557056": "NO",
    "565248": "PL",
    "573440": "US",
    "580432": "CH",
    "580436": "US",
    "581632": "RU",
    "585728": "GB",
    "589824": "UA",
    "593920": "GB",
    "594944": "BA",
    "595968": "ES",
    "598016": "DE",
    "606208": "IT",
    "610304": "RU",
    "614400": "DE",
    "622592": "IS",
    "626688": "RU",
    "630784": "PL",
    "638976": "GB",
    "643072": "SE",
    "647168": "BG",
    "651264": "LT",
    "655360": "DE",
    "659456": "DK",
    "663552": "RU",
    "667648": "DE",
    "675840": "ES",
    "679936": "SE",
    "688128": "GB",
    "704512": "RO",
    "712704": "US",
    "712960": "IE",
    "713216": "HK",
    "713472": "US",
    "713984": "SG",
    "714240": "AU",
    "714496": "SG",
    "714752": "IE",
    "716800": "BG",
    "720896": "IT",
    "724992": "IR",
    "729088": "CH",
    "733184": "DE",
    "737280": "KZ",
    "741376": "IT",
    "745472": "ES",
    "753664": "PL",
    "757760": "DE",
    "761856": "GE",
    "765952": "TJ",
    "770048": "DE",
    "774144": "CH",
    "778240": "CZ",
    "786432": "GB",
    "786944": "IE",
    "789888": "GB",
    "790016": "IE",
    "790528": "ES",
    "794624": "RU",
    "798720": "SK",
    "801024": "HU",
    "801280": "SK",
    "802816": "RU",
    "806912": "UZ",
    "811008": "RU",
    "815104": "MD",
    "819200": "IT",
    "823296": "DK",
    "827392": "IT",
    "835584": "UA",
    "837632": "NL",
    "838144": "BG",
    "838656": "UA",
    "839168": "PL",
    "839680": "NL",
    "840192": "UA",
    "842240": "NL",
    "842496": "UA",
    "843776": "SA",
    "847872": "RU",
    "851968": "NO",
    "860160": "HU",
    "864256": "FR",
    "868352": "DE",
    "872448": "ES",
    "876544": "HU",
    "880640": "ES",
    "884736": "GB",
    "892928": "DE",
    "897024": "AT",
    "901120": "DE",
    "905216": "RU",
    "909312": "SE",
    "916778": "NO",
    "916779": "SE",
    "916800": "NO",
    "916816": "SE",
    "917504": "NO",
    "921600": "RU",
    "925696": "ES",
    "929792": "RU",
    "933888": "CH",
    "937984": "NG",
    "942080": "AZ",
    "946176": "DE",
    "950272": "GB",
    "954368": "DE",
    "962560": "GB",
    "966656": "RU",
    "970752": "HR",
    "974848": "AT",
    "978944": "RU",
    "983040": "AT",
    "987136": "RU",
    "991232": "ES",
    "995328": "RU",
    "999424": "GB",
    "1003520": "FR",
    "1007616": "MT",
    "1011712": "GB",
    "1011968": "ZW",
    "1012480": "GB",
    "1012736": "ZW",
    "1015552": "GB",
    "1015808": "RU",
    "1024000": "DK",
    "1028096": "KZ",
    "1032192": "RU",
    "1036288": "IT",
    "1040384": "BE",
    "1044480": "SE",
    "1048576": "FR",
    "1052672": "RU",
    "1056768": "NL",
    "1060864": "GB",
    "1064960": "MK",
    "1073152": "DK",
    "1077248": "AT",
    "1081344": "RS",
    "1085440": "ES",
    "1089536": "DE",
    "1093632": "CZ",
    "1097728": "SE",
    "1101824": "GB",
    "1105920": "CY",
    "1110016": "ES",
    "1114112": "NO",
    "1118208": "DE",
    "1122304": "PL",
    "1126400": "GB",
    "1130496": "SE",
    "1134592": "LT",
    "1138214": "CD",
    "1138215": "LT",
    "1138688": "RS",
    "1142784": "RU",
    "1146880": "NL",
    "1150976": "TR",
    "1155072": "RU",
    "1163264": "DE",
    "1167360": "NO",
    "1171456": "BH",
    "1179648": "IT",
    "1183744": "AU",
    "1184000": "GB",
    "1184256": "AU",
    "1184768": "GB",
    "1187840": "ES",
    "1191936": "DE",
    "1192960": "IN",
    "1193984": "US",
    "1195008": "RU",
    "1196032": "NL",
    "1200384": "DE",
    "1200640": "FR",
    "1200896": "NL",
    "1201152": "GB",
    "1201408": "TR",
    "1201664": "FR",
    "1202176": "AZ",
    "1202432": "BE",
    "1202688": "NL",
    "1202944": "PK",
    "1203200": "IT",
    "1203456": "LV",
    "1203712": "IT",
    "1203968": "NL",
    "1204224": "IT",
    "1212416": "RU",
    "1220608": "ES",
    "1224704": "DE",
    "1228800": "NO",
    "1232896": "US",
    "1233920": "GB",
    "1234944": "UA",
    "1235968": "FR",
    "1236992": "ES",
    "1241088": "BG",
    "1245184": "RO",
    "1245440": "ES",
    "1245696": "NL",
    "1245952": "RO",
    "1246208": "AE",
    "1246464": "RO",
    "1247744": "NL",
    "1248000": "RO",
    "1248512": "DE",
    "1248768": "RO",
    "1249280": "NL",
    "1253376": "AT",
    "1257472": "FR",
    "1261568": "GR",
    "1269760": "RU",
    "1277952": "GB",
    "1282048": "IT",
    "1286144": "DE",
    "1294336": "FR",
    "1298432": "MD",
    "1302528": "BE",
    "1306624": "GB",
    "1310720": "IT",
    "1314816": "GB",
    "1318912": "NL",
    "1323008": "US",
    "1327104": "RU",
    "1335296": "SE",
    "1339392": "DE",
    "1343488": "HU",
    "1347584": "RU",
    "1351680": "UA",
    "1359872": "CH",
    "1363968": "SY",
    "1368064": "EG",
    "1372160": "US",
    "1373184": "GB",
    "1374208": "IT",
    "1375232": "IR",
    "1375488": "AL",
    "1376256": "PS",
    "1380352": "HU",
    "1384448": "BY",
    "1392640": "US",
    "1393664": "GB",
    "1394688": "SG",
    "1395712": "US",
    "1396736": "IN",
    "1400832": "RU",
    "1404928": "KE",
    "1409024": "IT",
    "1412608": "CA",
    "1412864": "IT",
    "1413120": "AL",
    "1417216": "LV",
    "1421312": "BE",
    "1425408": "NL",
    "1429504": "RU",
    "1433600": "SE",
    "1437696": "NL",
    "1441792": "GB",
    "1445888": "NL",
    "1448960": "US",
    "1449984": "NO",
    "1454080": "BE",
    "1458176": "SE",
    "1462272": "GB",
    "1466368": "ES",
    "1470464": "IL",
    "1474560": "CH",
    "1478656": "GB",
    "1482752": "RU",
    "1486848": "MT",
    "1490944": "DE",
    "1495040": "IT",
    "1507328": "NL",
    "1511424": "RU",
    "1515520": "JO",
    "1519616": "DE",
    "1523712": "RU",
    "1531904": "DK",
    "1536000": "BY",
    "1540096": "RU",
    "1545472": "NL",
    "1545728": "RU",
    "1548288": "IM",
    "1552384": "RU",
    "1556480": "BA",
    "1560576": "ES",
    "1564672": "GB",
    "1568768": "SK",
    "1572864": "DE",
    "1576960": "RS",
    "1581056": "DE",
    "1589248": "LV",
    "1593344": "FR",
    "1597440": "FI",
    "1601536": "RU",
    "1605632": "BA",
    "1609728": "IR",
    "1613824": "UA",
    "1617920": "RU",
    "1622016": "DE",
    "1634304": "AL",
    "1638400": "GB",
    "1642496": "AZ",
    "1646592": "SE",
    "1650688": "IR",
    "1654784": "DE",
    "1658880": "RU",
    "1661696": "PL",
    "1661952": "RU",
    "1662720": "PL",
    "1662976": "FI",
    "1667072": "AT",
    "1671168": "DE",
    "1675264": "RU",
    "1679360": "DE",
    "1683456": "FR",
    "1687552": "UA",
    "1691648": "RU",
    "1699840": "SE",
    "1703936": "RU",
    "1712128": "CH",
    "1720320": "RS",
    "1724416": "IT",
    "1728512": "NL",
    "1736704": "SA",
    "1738752": "FR",
    "1740800": "MD",
    "1748992": "IT",
    "1751040": "PL",
    "1752064": "ES",
    "1752576": "PE",
    "1752832": "VE",
    "1753088": "FR",
    "1757184": "RS",
    "1761280": "DE",
    "1763328": "GB",
    "1765376": "DE",
    "1773568": "GB",
    "1777664": "CY",
    "1785856": "IT",
    "1794048": "CH",
    "1798144": "IT",
    "1802240": "RU",
    "1806336": "UA",
    "1810432": "SE",
    "1811456": "DK",
    "1811968": "SE",
    "1818624": "DE",
    "1822720": "HU",
    "1826816": "NL",
    "1830912": "GB",
    "1835008": "IM",
    "1839104": "GB",
    "1841152": "CA",
    "1843200": "SE",
    "1843844": "",
    "1843845": "SE",
    "1847296": "LV",
    "1851392": "IT",
    "1853440": "RU",
    "1855488": "CZ",
    "1859584": "DE",
    "1863680": "IT",
    "1867776": "LT",
    "1868032": "DE",
    "1868288": "IN",
    "1868544": "PL",
    "1868800": "RU",
    "1869056": "IE",
    "1869312": "PL",
    "1869568": "NL",
    "1869824": "IT",
    "1870080": "RO",
    "1870336": "NL",
    "1870592": "TR",
    "1870848": "UA",
    "1871104": "RU",
    "1871360": "PL",
    "1871616": "PT",
    "1871872": "PL",
    "1875968": "DK",
    "1876736": "US",
    "1876992": "DK",
    "1880064": "IS",
    "1884160": "SE",
    "1888256": "RU",
    "1896448": "NL",
    "1896792": "EE",
    "1896794": "NL",
    "1896816": "EE",
    "1896817": "NL",
    "1896960": "EE",
    "1896976": "NL",
    "1897216": "LV",
    "1897222": "NL",
    "1897236": "LV",
    "1897238": "NL",
    "1897244": "LV",
    "1897268": "NL",
    "1897284": "LV",
    "1897304": "NL",
    "1897312": "LV",
    "1897320": "NL",
    "1897470": "LV",
    "1897472": "RU",
    "1897728": "HU",
    "1897732": "NL",
    "1897733": "RU",
    "1897734": "NL",
    "1897744": "DE",
    "1897752": "NL",
    "1897786": "DE",
    "1897788": "LT",
    "1897792": "DE",
    "1897796": "PL",
    "1897800": "NL",
    "1897804": "DE",
    "1897808": "NL",
    "1897836": "PL",
    "1897840": "HU",
    "1897848": "DE",
    "1897852": "HU",
    "1897856": "NL",
    "1897864": "EE",
    "1897868": "LV",
    "1897872": "PL",
    "1897876": "RU",
    "1897880": "HU",
    "1897884": "LT",
    "1897888": "NL",
    "1897984": "RU",
    "1898496": "LT",
    "1898752": "LV",
    "1899008": "NL",
    "1899024": "DE",
    "1899040": "NL",
    "1899060": "DE",
    "1899072": "NL",
    "1899078": "DE",
    "1899080": "NL",
    "1899088": "DE",
    "1899096": "NL",
    "1899104": "DE",
    "1899106": "NL",
    "1899112": "DE",
    "1899116": "NL",
    "1899216": "DE",
    "1899240": "NL",
    "1899246": "DE",
    "1899264": "NL",
    "1899328": "LT",
    "1899332": "NL",
    "1899358": "LT",
    "1899360": "NL",
    "1899384": "LT",
    "1899388": "NL",
    "1899392": "LT",
    "1899400": "NL",
    "1899408": "LT",
    "1899418": "NL",
    "1899488": "LT",
    "1899496": "NL",
    "1899536": "PL",
    "1899556": "NL",
    "1899560": "PL",
    "1899570": "NL",
    "1899578": "PL",
    "1899580": "NL",
    "1899600": "PL",
    "1899602": "NL",
    "1899614": "PL",
    "1899618": "NL",
    "1899620": "PL",
    "1899622": "NL",
    "1899624": "PL",
    "1899632": "NL",
    "1899636": "PL",
    "1899640": "NL",
    "1899648": "PL",
    "1899700": "NL",
    "1899704": "PL",
    "1899712": "NL",
    "1899720": "PL",
    "1899736": "NL",
    "1899792": "SE",
    "1899810": "NL",
    "1899818": "SE",
    "1899824": "NL",
    "1899846": "SE",
    "1899850": "NL",
    "1899856": "SE",
    "1899864": "NL",
    "1899872": "SE",
    "1899888": "NL",
    "1899892": "SE",
    "1899894": "NL",
    "1899896": "SE",
    "1899904": "NL",
    "1899936": "SE",
    "1899952": "NL",
    "1899956": "SE",
    "1899960": "NL",
    "1899968": "SE",
    "1900032": "NL",
    "1900288": "DE",
    "1900290": "NL",
    "1900544": "CZ",
    "1904640": "KG",
    "1908736": "DE",
    "1912832": "RU",
    "1916928": "IT",
    "1921024": "RU",
    "1925120": "ES",
    "1929216": "UZ",
    "1933312": "TZ",
    "1937408": "AT",
    "1941504": "IT",
    "1945600": "RU",
    "1949696": "GB",
    "1953792": "ZA",
    "1957888": "AX",
    "1961984": "JO",
    "1966080": "IT",
    "1967104": "PL",
    "1969152": "BE",
    "1970240": "ER",
    "1970241": "BE",
    "1972736": "",
    "1972992": "BE",
    "1974272": "DK",
    "1978368": "DE",
    "1982464": "CZ",
    "1986560": "US",
    "1988615": "CH",
    "1988616": "US",
    "1990656": "MT",
    "1994752": "GB",
    "1998848": "PL",
    "2007040": "UZ",
    "2011136": "FI",
    "2015232": "UA",
    "2019328": "BG",
    "2023424": "DE",
    "2027520": "RU",
    "2031616": "GB",
    "2035712": "DE",
    "2039808": "SK",
    "2040064": "PL",
    "2040192": "SK",
    "2043904": "CZ",
    "2048000": "LU",
    "2052096": "DE",
    "2056192": "NO",
    "2060288": "IT",
    "2064384": "GB",
    "2072576": "SE",
    "2080768": "CZ",
    "2084864": "DE",
    "2088960": "TR",
    "2097152": "GB",
    "2202624": "US",
    "2203136": "GB",
    "2865152": "US",
    "2865280": "GB",
    "3145728": "DE",
    "3407872": "EG",
    "3670016": "IT",
    "3932160": "IR",
    "3997696": "DE",
    "3999744": "IT",
    "4001792": "GB",
    "4003840": "IT",
    "4014080": "ES",
    "4022272": "FR",
    "4024320": "DE",
    "4026368": "GB",
    "4028416": "IT",
    "4030464": "ES",
    "4034560": "DE",
    "4038656": "IT",
    "4042752": "GB",
    "4046848": "DE",
    "4050944": "ES",
    "4052992": "DK",
    "4055040": "ES",
    "4056064": "GB",
    "4057088": "DE",
    "4058112": "DK",
    "4059136": "ES",
    "4060160": "SE",
    "4061184": "DE",
    "4061696": "DK",
    "4062208": "SI",
    "4062464": "NL",
    "4062720": "IT",
    "4062976": "DE",
    "4063232": "NL",
    "4153344": "FR",
    "4153345": "DK",
    "4157440": "SE",
    "4158464": "DK",
    "4161536": "NL",
    "4194304": "CZ",
    "4198400": "AZ",
    "4202496": "FI",
    "4206592": "FR",
    "4210688": "DE",
    "4218880": "ML",
    "4222976": "GB",
    "4223232": "IT",
    "4223488": "GB",
    "4226816": "AT",
    "4227072": "RU",
    "4231168": "UA",
    "4232192": "SE",
    "4232960": "US",
    "4233216": "RU",
    "4234240": "FR",
    "4235264": "DE",
    "4239360": "FI",
    "4243456": "IT",
    "4247552": "TR",
    "4251648": "DE",
    "4253696": "GB",
    "4254720": "DE",
    "4255744": "BE",
    "4259840": "RU",
    "4263936": "DE",
    "4268032": "IL",
    "4269056": "US",
    "4269312": "IL",
    "4269568": "US",
    "4269824": "IL",
    "4270592": "US",
    "4270848": "IL",
    "4272128": "GI",
    "4276224": "IT",
    "4280320": "RU",
    "4284416": "HU",
    "4292608": "DE",
    "4293376": "NL",
    "4293632": "SE",
    "4294656": "FR",
    "4294688": "DK",
    "4294720": "EG",
    "4294752": "CZ",
    "4294784": "CH",
    "4294816": "PT",
    "4294848": "EE",
    "4294880": "NO",
    "4294912": "FR",
    "4294944": "DK",
    "4294976": "EG",
    "4295008": "CZ",
    "4295040": "CH",
    "4295072": "PT",
    "4295104": "PL",
    "4295168": "GR",
    "4295200": "DK",
    "4295232": "EG",
    "4295264": "CZ",
    "4295296": "CH",
    "4295328": "PT",
    "4295360": "ES",
    "4295392": "DK",
    "4295424": "GR",
    "4295456": "DK",
    "4295488": "EG",
    "4295520": "CZ",
    "4295552": "CH",
    "4295584": "PT",
    "4295616": "ES",
    "4295648": "DK",
    "4295680": "NG",
    "4295744": "MZ",
    "4295808": "RW",
    "4295872": "PL",
    "4295936": "PT",
    "4296064": "FR",
    "4296192": "NL",
    "4296320": "IE",
    "4296448": "ES",
    "4296576": "DE",
    "4296704": "GB",
    "4304896": "TR",
    "4308992": "RS",
    "4313088": "RU",
    "4317184": "NO",
    "4321280": "UA",
    "4325376": "BE",
    "4329472": "RU",
    "4333568": "DE",
    "4341760": "RU",
    "4349952": "UA",
    "4354048": "FR",
    "4358144": "DE",
    "4362240": "RU",
    "4366336": "CZ",
    "4374272": "SK",
    "4374528": "IR",
    "4382720": "PS",
    "4390912": "RU",
    "4395008": "SK",
    "4399104": "DE",
    "4403200": "GB",
    "4408320": "US",
    "4409344": "FR",
    "4409856": "ES",
    "4410368": "IT",
    "4410880": "NO",
    "4411392": "SE",
    "4415488": "DE",
    "4419584": "RU",
    "4423680": "CH",
    "4427776": "FR",
    "4431872": "ES",
    "4435968": "RU",
    "4440064": "PL",
    "4448256": "NL",
    "4456448": "DE",
    "4460544": "NL",
    "4464640": "SE",
    "4468736": "NL",
    "4472832": "GB",
    "4476928": "HR",
    "4481024": "NO",
    "4489216": "GB",
    "4493312": "DE",
    "4505600": "GB",
    "4509696": "TR",
    "4513792": "CH",
    "4517888": "GB",
    "4521984": "FR",
    "4530176": "GB",
    "4534272": "FI",
    "4538368": "DE",
    "4546560": "CZ",
    "4550656": "LV",
    "4552960": "US",
    "4553216": "LV",
    "4553984": "US",
    "4554752": "RU",
    "4558848": "SE",
    "4562944": "DE",
    "4567040": "KW",
    "4571136": "RU",
    "4579328": "DE",
    "4587520": "ES",
    "4591616": "RU",
    "4595712": "SE",
    "4599808": "PL",
    "4603904": "PT",
    "4608000": "FR",
    "4612096": "RU",
    "4620288": "DE",
    "4624384": "IT",
    "4628480": "DE",
    "4632576": "FR",
    "4633024": "LU",
    "4633088": "FR",
    "4636672": "DE",
    "4640768": "NL",
    "4644864": "GB",
    "4646140": "BE",
    "4646141": "GB",
    "4648960": "ES",
    "4653056": "DK",
    "4657152": "ES",
    "4661248": "EE",
    "4665344": "BA",
    "4669440": "IT",
    "4673536": "CH",
    "4677632": "DE",
    "4681728": "US",
    "4684800": "FR",
    "4685824": "RU",
    "4689920": "FI",
    "4694016": "RU",
    "4698112": "MT",
    "4702208": "PL",
    "4702996": "ES",
    "4702997": "PL",
    "4704256": "ES",
    "4706304": "FR",
    "4708352": "DE",
    "4710400": "RU",
    "4714496": "CH",
    "4718592": "RU",
    "4721664": "CY",
    "4722688": "SE",
    "4726784": "IT",
    "4730880": "SE",
    "4734976": "SI",
    "4743168": "IT",
    "4747264": "GB",
    "4751360": "DE",
    "4755456": "RU",
    "4759552": "GB",
    "4767744": "DE",
    "4775936": "BE",
    "4780032": "GB",
    "4784128": "SE",
    "4788224": "SK",
    "4792320": "DE",
    "4798464": "RU",
    "4800512": "GB",
    "4804608": "UA",
    "4808704": "SE",
    "4812800": "RU",
    "4816896": "AL",
    "4820992": "DE",
    "4825088": "RO",
    "4829184": "PL",
    "4833280": "RU",
    "4837376": "IT",
    "4845568": "PL",
    "4849664": "DE",
    "4851712": "AT",
    "4853760": "ES",
    "4854016": "NL",
    "4854528": "SE",
    "4854784": "NL",
    "4855808": "TR",
    "4857856": "RU",
    "4861952": "IE",
    "4866048": "PL",
    "4870144": "SE",
    "4874240": "FR",
    "4878336": "RU",
    "4882432": "SE",
    "4886528": "DK",
    "4890624": "RU",
    "4894720": "DE",
    "4902912": "DK",
    "4907008": "GB",
    "4911104": "RU",
    "4915200": "IE",
    "4919296": "CH",
    "4923392": "NL",
    "4927488": "PL",
    "4931584": "SK",
    "4939776": "SE",
    "4947968": "BG",
    "4956160": "FR",
    "4960256": "AT",
    "4964352": "BA",
    "4968448": "CZ",
    "4972544": "ES",
    "4980736": "AM",
    "4984832": "NL",
    "4988928": "RU",
    "4993024": "DE",
    "4997120": "KZ",
    "5001216": "SE",
    "5005312": "DE",
    "5009408": "PL",
    "5013504": "ES",
    "5021696": "AT",
    "5025792": "RU",
    "5029888": "UA",
    "5033984": "IT",
    "5038080": "BE",
    "5042176": "ES",
    "5046272": "GB",
    "5050368": "LT",
    "5054464": "NO",
    "5058560": "RU",
    "5062656": "GA",
    "5066752": "IT",
    "5070848": "RU",
    "5072128": "IN",
    "5072384": "RU",
    "5072640": "IN",
    "5072896": "RU",
    "5074944": "IR",
    "5079040": "NL",
    "5087232": "CZ",
    "5091328": "GB",
    "5095424": "FI",
    "5099520": "UA",
    "5103616": "FR",
    "5107712": "DE",
    "5111808": "IE",
    "5115904": "SE",
    "5124096": "PS",
    "5132288": "GB",
    "5134848": "US",
    "5135104": "GB",
    "5136128": "AU",
    "5136384": "TR",
    "5140480": "CH",
    "5144576": "DE",
    "5148672": "GB",
    "5152768": "DE",
    "5156864": "RU",
    "5160960": "FI",
    "5169152": "RU",
    "5171456": "AE",
    "5171712": "RU",
    "5172480": "FI",
    "5172736": "SA",
    "5172992": "EE",
    "5173248": "CW",
    "5177344": "RU",
    "5185536": "BG",
    "5189632": "RU",
    "5193728": "BG",
    "5201920": "GB",
    "5210112": "HU",
    "5214208": "PL",
    "5215232": "RS",
    "5216256": "PL",
    "5218304": "GB",
    "5222400": "DE",
    "5226496": "CH",
    "5230592": "DE",
    "5232640": "",
    "5232896": "DE",
    "5234688": "RU",
    "5238784": "US",
    "5239040": "SG",
    "5239072": "US",
    "5239104": "SG",
    "5239168": "US",
    "5239192": "SG",
    "5239200": "US",
    "5239232": "SG",
    "5239296": "US",
    "5240320": "AU",
    "5240576": "US",
    "5242880": "DE",
    "5587549": "US",
    "5587550": "DE",
    "6291456": "PL",
    "6553600": "NL",
    "6946816": "RU",
    "7077888": "FR",
    "7103488": "GF",
    "7103744": "FR",
    "7104000": "GF",
    "7104512": "FR",
    "7208960": "DE",
    "7222048": "BE",
    "7222056": "DE",
    "7228016": "DK",
    "7228024": "DE",
    "7228992": "ES",
    "7229008": "DE",
    "7233792": "BE",
    "7233800": "DE",
    "7235504": "CH",
    "7235512": "DE",
    "7242264": "GB",
    "7242272": "DE",
    "7242464": "GB",
    "7242466": "DE",
    "7243064": "GB",
    "7243072": "DE",
    "7243136": "GB",
    "7243144": "DE",
    "7243184": "GB",
    "7243192": "DE",
    "7246096": "GB",
    "7246104": "DE",
    "7246496": "IE",
    "7246504": "DE",
    "7249408": "GB",
    "7249664": "FR",
    "7249668": "GB",
    "7249680": "DE",
    "7249684": "GB",
    "7249700": "DE",
    "7249704": "GB",
    "7249712": "DE",
    "7249716": "GB",
    "7249732": "DE",
    "7249736": "GB",
    "7249740": "DE",
    "7249744": "GB",
    "7249808": "DE",
    "7249816": "GB",
    "7249828": "DE",
    "7249832": "GB",
    "7249856": "DE",
    "7249864": "GB",
    "7249880": "DE",
    "7249884": "GB",
    "7249896": "DE",
    "7249900": "GB",
    "7249908": "DE",
    "7249916": "GB",
    "7249920": "DE",
    "7249924": "GB",
    "7249928": "DE",
    "7253328": "GB",
    "7253336": "DE",
    "7253432": "BE",
    "7253440": "DE",
    "7255288": "FR",
    "7255296": "DE",
    "7263232": "ES",
    "7263488": "DE",
    "7263760": "GB",
    "7263776": "DE",
    "7263808": "GB",
    "7263920": "DE",
    "7263928": "GB",
    "7264032": "DE",
    "7264048": "GB",
    "7264096": "DE",
    "7264104": "GB",
    "7264116": "DE",
    "7264120": "GB",
    "7264160": "DE",
    "7264176": "GB",
    "7264208": "DE",
    "7264224": "GB",
    "7264240": "DE",
    "7264248": "GB",
    "7264256": "DE",
    "7266440": "BE",
    "7266448": "DE",
    "7270184": "FR",
    "7270192": "DE",
    "7271832": "BE",
    "7271840": "DE",
    "7280128": "DK",
    "7280200": "DE",
    "7280256": "SE",
    "7280272": "DE",
    "7280280": "DK",
    "7280288": "DE",
    "7280312": "DK",
    "7280320": "DE",
    "7285264": "BE",
    "7285272": "DE",
    "7285368": "BE",
    "7285376": "DE",
    "7286124": "FR",
    "7286128": "DE",
    "7290072": "CZ",
    "7290080": "DE",
    "7291432": "GB",
    "7291440": "DE",
    "7296852": "FR",
    "7296856": "DE",
    "7297748": "CH",
    "7297752": "DE",
    "7303384": "ES",
    "7303388": "DE",
    "7304316": "AT",
    "7304320": "DE",
    "7306480": "BE",
    "7306488": "DE",
    "7307296": "BE",
    "7307312": "DE",
    "7307336": "BE",
    "7307344": "DE",
    "7307360": "BE",
    "7307368": "DE",
    "7307392": "BE",
    "7307400": "NL",
    "7307408": "BE",
    "7307456": "DE",
    "7307472": "BE",
    "7307480": "DE",
    "7307488": "BE",
    "7307496": "DE",
    "7307544": "BE",
    "7307616": "DE",
    "7308288": "ES",
    "7308544": "SE",
    "7308548": "DK",
    "7308552": "SE",
    "7308556": "DK",
    "7308560": "SE",
    "7308564": "DK",
    "7308608": "NO",
    "7308616": "DK",
    "7308636": "SE",
    "7308640": "DK",
    "7308644": "DE",
    "7308648": "SE",
    "7308652": "NO",
    "7308656": "DE",
    "7308660": "DK",
    "7308664": "DE",
    "7309312": "BE",
    "7309344": "ES",
    "7309568": "DE",
    "7309572": "ES",
    "7309592": "DE",
    "7309596": "ES",
    "7309612": "DE",
    "7309640": "ES",
    "7309656": "DE",
    "7309660": "ES",
    "7309676": "DE",
    "7309680": "ES",
    "7309684": "DE",
    "7309696": "ES",
    "7309724": "DE",
    "7309728": "ES",
    "7309736": "DE",
    "7309744": "ES",
    "7309772": "DE",
    "7309776": "ES",
    "7309788": "DE",
    "7309804": "ES",
    "7309824": "GB",
    "7310888": "DE",
    "7310896": "GB",
    "7310904": "DE",
    "7310912": "GB",
    "7311360": "BE",
    "7311384": "DE",
    "7311388": "BE",
    "7311408": "DE",
    "7311412": "BE",
    "7311424": "DE",
    "7311426": "BE",
    "7311428": "DE",
    "7311440": "BE",
    "7311456": "DE",
    "7311464": "BE",
    "7311472": "DE",
    "7311476": "BE",
    "7311488": "DE",
    "7311492": "BE",
    "7311496": "DE",
    "7311504": "BE",
    "7311520": "DE",
    "7311524": "BE",
    "7311528": "DE",
    "7311532": "BE",
    "7311548": "DE",
    "7311552": "BE",
    "7311568": "DE",
    "7311576": "BE",
    "7311586": "DE",
    "7311592": "BE",
    "7311596": "DE",
    "7311604": "BE",
    "7311612": "DE",
    "7311616": "BE",
    "7311632": "LU",
    "7311640": "BE",
    "7311784": "LU",
    "7311792": "BE",
    "7311840": "LU",
    "7311848": "BE",
    "7311984": "DE",
    "7311992": "BE",
    "7312384": "FR",
    "7313408": "IT",
    "7313920": "BE",
    "7314040": "NL",
    "7314048": "BE",
    "7314144": "LU",
    "7314176": "BE",
    "7314432": "FR",
    "7315456": "IT",
    "7315968": "GB",
    "7316272": "DE",
    "7316280": "GB",
    "7317504": "IT",
    "7317600": "DE",
    "7317608": "IT",
    "7317640": "DE",
    "7317648": "IT",
    "7317680": "DE",
    "7317696": "IT",
    "7317712": "DE",
    "7317728": "IT",
    "7317768": "DE",
    "7317776": "IT",
    "7317792": "DE",
    "7317800": "IT",
    "7317880": "DE",
    "7317888": "IT",
    "7317896": "DE",
    "7317904": "IT",
    "7317984": "DE",
    "7317992": "IT",
    "7318292": "DE",
    "7318296": "IT",
    "7318300": "DE",
    "7318308": "IT",
    "7318312": "DE",
    "7318320": "IT",
    "7318324": "DE",
    "7318328": "IT",
    "7318348": "DE",
    "7318352": "IT",
    "7318372": "DE",
    "7318380": "IT",
    "7318388": "DE",
    "7318392": "IT",
    "7318400": "DE",
    "7318408": "IT",
    "7318416": "DE",
    "7318420": "IT",
    "7318424": "DE",
    "7318428": "IT",
    "7318440": "DE",
    "7318448": "IT",
    "7318468": "DE",
    "7318476": "IT",
    "7318480": "DE",
    "7318484": "IT",
    "7318488": "DE",
    "7318492": "IT",
    "7318524": "DE",
    "7318528": "ES",
    "7318530": "DE",
    "7318536": "ES",
    "7318556": "DE",
    "7318564": "ES",
    "7318600": "DE",
    "7318604": "ES",
    "7318616": "DE",
    "7318620": "ES",
    "7318668": "DE",
    "7318672": "ES",
    "7318676": "DE",
    "7318684": "ES",
    "7318692": "DE",
    "7318696": "ES",
    "7318708": "DE",
    "7318716": "ES",
    "7318740": "DE",
    "7318744": "ES",
    "7318756": "DE",
    "7318760": "ES",
    "7318768": "DE",
    "7318772": "ES",
    "7318804": "DE",
    "7318808": "ES",
    "7318816": "DE",
    "7318824": "PT",
    "7318828": "ES",
    "7318832": "DE",
    "7318836": "ES",
    "7318852": "DE",
    "7318860": "ES",
    "7318864": "DE",
    "7318868": "ES",
    "7318876": "DE",
    "7318878": "ES",
    "7318880": "DE",
    "7318888": "ES",
    "7318912": "DE",
    "7318944": "ES",
    "7318956": "DE",
    "7318960": "ES",
    "7318996": "DE",
    "7319000": "ES",
    "7319008": "DE",
    "7319012": "ES",
    "7319016": "DE",
    "7319020": "ES",
    "7319144": "BE",
    "7319152": "ES",
    "7319556": "DE",
    "7319564": "ES",
    "7319584": "DE",
    "7319588": "ES",
    "7319592": "DE",
    "7319596": "ES",
    "7319604": "DE",
    "7319608": "ES",
    "7319632": "DE",
    "7319640": "ES",
    "7319644": "DE",
    "7319648": "ES",
    "7319666": "DE",
    "7319668": "ES",
    "7319672": "DE",
    "7319676": "ES",
    "7319684": "DE",
    "7319688": "ES",
    "7319700": "DE",
    "7319704": "ES",
    "7319724": "DE",
    "7319728": "ES",
    "7319732": "DE",
    "7319736": "ES",
    "7319764": "DE",
    "7319768": "ES",
    "7319780": "DE",
    "7319784": "ES",
    "7319800": "DE",
    "7319804": "ES",
    "7319816": "DE",
    "7319826": "ES",
    "7319840": "GB",
    "7319856": "ES",
    "7319868": "DE",
    "7319872": "ES",
    "7319880": "DE",
    "7319884": "ES",
    "7319908": "DE",
    "7319912": "ES",
    "7319916": "DE",
    "7319920": "ES",
    "7319952": "DE",
    "7319960": "ES",
    "7319964": "DE",
    "7319972": "ES",
    "7319984": "DE",
    "7319988": "ES",
    "7319996": "GB",
    "7320000": "ES",
    "7320008": "DE",
    "7320010": "ES",
    "7320012": "DE",
    "7320016": "ES",
    "7320032": "DE",
    "7320040": "ES",
    "7320044": "DE",
    "7320050": "ES",
    "7320576": "BE",
    "7321344": "DE",
    "7321348": "BE",
    "7321372": "NL",
    "7321376": "LU",
    "7321380": "BE",
    "7321392": "NL",
    "7321396": "BE",
    "7321400": "DE",
    "7321408": "BE",
    "7321412": "DE",
    "7321416": "BE",
    "7321424": "DE",
    "7321432": "BE",
    "7321448": "DE",
    "7321460": "BE",
    "7321468": "DE",
    "7321484": "BE",
    "7321500": "DE",
    "7321504": "BE",
    "7321508": "DE",
    "7321512": "BE",
    "7321540": "DE",
    "7321552": "BE",
    "7321580": "DE",
    "7321584": "BE",
    "7321600": "GB",
    "7321920": "IE",
    "7321984": "GB",
    "7322560": "FR",
    "7322564": "GB",
    "7322624": "NL",
    "7322640": "DE",
    "7322644": "NL",
    "7322664": "DE",
    "7322668": "NL",
    "7322688": "DE",
    "7322690": "NL",
    "7322758": "DE",
    "7322760": "NL",
    "7322784": "DE",
    "7322788": "NL",
    "7322796": "DE",
    "7322800": "NL",
    "7322804": "DE",
    "7322808": "NL",
    "7322812": "DE",
    "7322816": "NL",
    "7322824": "DE",
    "7322828": "NL",
    "7322836": "DE",
    "7322844": "NL",
    "7322848": "DE",
    "7322860": "NL",
    "7322872": "DE",
    "7322876": "NL",
    "7322888": "BE",
    "7322896": "NL",
    "7323136": "IT",
    "7323648": "FR",
    "7323680": "DE",
    "7323684": "FR",
    "7323696": "DE",
    "7323700": "FR",
    "7323712": "DE",
    "7323720": "FR",
    "7323732": "DE",
    "7323736": "FR",
    "7323748": "DE",
    "7323752": "FR",
    "7323756": "DE",
    "7323760": "FR",
    "7323772": "DE",
    "7323776": "FR",
    "7323780": "DE",
    "7323784": "FR",
    "7323792": "DE",
    "7323796": "FR",
    "7323800": "DE",
    "7323808": "FR",
    "7323832": "DE",
    "7323848": "FR",
    "7323860": "DE",
    "7323864": "FR",
    "7323868": "DE",
    "7323872": "FR",
    "7323892": "DE",
    "7323900": "FR",
    "7324672": "GB",
    "7324992": "DE",
    "7325000": "GB",
    "7325008": "BE",
    "7325016": "GB",
    "7325696": "NL",
    "7325700": "DE",
    "7325704": "BE",
    "7325708": "DE",
    "7325712": "NL",
    "7325716": "DE",
    "7325720": "BE",
    "7325724": "DE",
    "7325728": "BE",
    "7325730": "DE",
    "7325732": "BE",
    "7325740": "DE",
    "7325748": "BE",
    "7325764": "DE",
    "7325772": "BE",
    "7325788": "DE",
    "7325792": "BE",
    "7325800": "DE",
    "7325804": "BE",
    "7325812": "NL",
    "7325816": "DE",
    "7325820": "BE",
    "7325828": "DE",
    "7325832": "BE",
    "7325848": "DE",
    "7325856": "BE",
    "7325876": "DE",
    "7325880": "BE",
    "7325884": "DE",
    "7325888": "BE",
    "7325892": "DE",
    "7325900": "BE",
    "7325916": "DE",
    "7325920": "BE",
    "7325944": "NL",
    "7325948": "BE",
    "7326400": "LU",
    "7326416": "BE",
    "7326468": "DE",
    "7326472": "BE",
    "7326476": "DE",
    "7326488": "BE",
    "7326500": "DE",
    "7326504": "BE",
    "7326512": "DE",
    "7326516": "BE",
    "7326520": "NL",
    "7326524": "DE",
    "7326536": "BE",
    "7326540": "DE",
    "7326544": "BE",
    "7326548": "DE",
    "7326552": "BE",
    "7326560": "DE",
    "7326566": "BE",
    "7326580": "DE",
    "7326584": "BE",
    "7326596": "DE",
    "7326600": "BE",
    "7326616": "DE",
    "7326624": "BE",
    "7326628": "DE",
    "7326632": "BE",
    "7326640": "NL",
    "7326644": "BE",
    "7326648": "DE",
    "7326652": "BE",
    "7326680": "DE",
    "7326684": "BE",
    "7326696": "NL",
    "7326700": "BE",
    "7326712": "NL",
    "7326716": "BE",
    "7326720": "IT",
    "7326728": "DE",
    "7326732": "IT",
    "7326756": "DE",
    "7326760": "IT",
    "7326764": "DE",
    "7326768": "IT",
    "7326776": "DE",
    "7326780": "IT",
    "7326784": "DE",
    "7326796": "IT",
    "7326800": "DE",
    "7326804": "IT",
    "7326816": "DE",
    "7326820": "IT",
    "7326824": "DE",
    "7326832": "IT",
    "7326844": "DE",
    "7326848": "IT",
    "7326852": "DE",
    "7326864": "IT",
    "7326880": "DE",
    "7326884": "IT",
    "7326896": "DE",
    "7326900": "IT",
    "7326908": "DE",
    "7326916": "IT",
    "7326920": "DE",
    "7326940": "IT",
    "7326944": "DE",
    "7326956": "IT",
    "7326968": "DE",
    "7326972": "IT",
    "7327248": "AT",
    "7327256": "IT",
    "7327272": "BE",
    "7327280": "ES",
    "7327288": "IT",
    "7327744": "GB",
    "7328768": "DE",
    "7329280": "BE",
    "7329592": "LU",
    "7329600": "BE",
    "7329624": "NL",
    "7329632": "BE",
    "7329792": "ES",
    "7329800": "GB",
    "7329804": "ES",
    "7329808": "DE",
    "7329816": "ES",
    "7329824": "DE",
    "7329828": "ES",
    "7329832": "DE",
    "7329836": "ES",
    "7329844": "DE",
    "7329852": "ES",
    "7329860": "DE",
    "7329862": "ES",
    "7329864": "DE",
    "7329872": "ES",
    "7329880": "DE",
    "7329884": "ES",
    "7329888": "DE",
    "7329892": "ES",
    "7329904": "DE",
    "7329908": "ES",
    "7329912": "DE",
    "7329920": "ES",
    "7329928": "DE",
    "7329948": "ES",
    "7329952": "DE",
    "7329960": "ES",
    "7329964": "DE",
    "7329976": "ES",
    "7329984": "DE",
    "7329988": "ES",
    "7329992": "DE",
    "7329996": "ES",
    "7330000": "DE",
    "7330004": "ES",
    "7330012": "DE",
    "7330016": "ES",
    "7330044": "DE",
    "7330048": "ES",
    "7330336": "FR",
    "7330344": "ES",
    "7330820": "DE",
    "7330824": "ES",
    "7330828": "DE",
    "7330832": "ES",
    "7330848": "DE",
    "7330852": "ES",
    "7330872": "DE",
    "7330876": "ES",
    "7330880": "DE",
    "7330884": "ES",
    "7330892": "DE",
    "7330894": "ES",
    "7330916": "DE",
    "7330920": "ES",
    "7330924": "DE",
    "7330928": "ES",
    "7330932": "DE",
    "7330936": "ES",
    "7330944": "DE",
    "7330948": "ES",
    "7330956": "DE",
    "7330964": "ES",
    "7330984": "DE",
    "7330988": "ES",
    "7330992": "DE",
    "7330996": "ES",
    "7331012": "DE",
    "7331024": "ES",
    "7331028": "DE",
    "7331032": "ES",
    "7331040": "DE",
    "7331052": "ES",
    "7331068": "DE",
    "7331072": "ES",
    "7331328": "DE",
    "7331332": "ES",
    "7331344": "DE",
    "7331348": "ES",
    "7331368": "DE",
    "7331372": "ES",
    "7331408": "DE",
    "7331412": "ES",
    "7331416": "DE",
    "7331420": "ES",
    "7331448": "DE",
    "7331452": "ES",
    "7331456": "DE",
    "7331460": "ES",
    "7331464": "DE",
    "7331468": "ES",
    "7331496": "DE",
    "7331500": "ES",
    "7331502": "DE",
    "7331516": "ES",
    "7331564": "DE",
    "7331568": "ES",
    "7331572": "DE",
    "7331576": "ES",
    "7331840": "IT",
    "7332096": "DE",
    "7332352": "IT",
    "7332864": "BE",
    "7332868": "DE",
    "7332872": "BE",
    "7332888": "DE",
    "7332892": "BE",
    "7332896": "NL",
    "7332900": "BE",
    "7332904": "DE",
    "7332916": "BE",
    "7332924": "DE",
    "7332928": "BE",
    "7332932": "DE",
    "7332940": "BE",
    "7332968": "DE",
    "7332972": "BE",
    "7332980": "DE",
    "7332984": "BE",
    "7332992": "DE",
    "7333056": "BE",
    "7333072": "DE",
    "7333074": "BE",
    "7333080": "DE",
    "7333084": "BE",
    "7333100": "DE",
    "7333108": "BE",
    "7333110": "DE",
    "7333116": "BE",
    "7333616": "LU",
    "7333624": "BE",
    "7333636": "DE",
    "7333648": "BE",
    "7333652": "DE",
    "7333664": "BE",
    "7333666": "LU",
    "7333668": "BE",
    "7333672": "DE",
    "7333676": "BE",
    "7333684": "DE",
    "7333692": "BE",
    "7333700": "DE",
    "7333712": "BE",
    "7333752": "DE",
    "7333764": "BE",
    "7333768": "DE",
    "7333776": "BE",
    "7333780": "DE",
    "7333784": "BE",
    "7333788": "DE",
    "7333796": "BE",
    "7333800": "DE",
    "7333816": "BE",
    "7333820": "DE",
    "7333824": "BE",
    "7333828": "DE",
    "7333832": "BE",
    "7333836": "DE",
    "7333840": "BE",
    "7333844": "DE",
    "7333848": "BE",
    "7333852": "DE",
    "7333856": "BE",
    "7333860": "DE",
    "7333864": "BE",
    "7333868": "LU",
    "7333870": "BE",
    "7333872": "NL",
    "7333876": "DE",
    "7333880": "BE",
    "7333884": "DE",
    "7334016": "ES",
    "7334048": "DE",
    "7334080": "FR",
    "7334112": "DE",
    "7334144": "ES",
    "7334400": "DE",
    "7334404": "ES",
    "7334416": "DE",
    "7334422": "ES",
    "7334424": "DE",
    "7334428": "ES",
    "7334448": "DE",
    "7334452": "ES",
    "7334464": "DE",
    "7334476": "ES",
    "7334480": "DE",
    "7334484": "ES",
    "7334504": "DE",
    "7334512": "ES",
    "7334516": "DE",
    "7334520": "ES",
    "7334524": "DE",
    "7334528": "ES",
    "7334536": "DE",
    "7334540": "ES",
    "7334556": "DE",
    "7334562": "ES",
    "7334564": "DE",
    "7334568": "ES",
    "7334572": "DE",
    "7334580": "ES",
    "7334584": "DE",
    "7334592": "ES",
    "7334602": "DE",
    "7334608": "ES",
    "7334612": "DE",
    "7334616": "ES",
    "7334620": "DE",
    "7334624": "ES",
    "7334640": "DE",
    "7334644": "ES",
    "7334832": "IT",
    "7334840": "ES",
    "7334914": "DE",
    "7334916": "ES",
    "7334924": "DE",
    "7334928": "ES",
    "7334936": "DE",
    "7334940": "ES",
    "7334952": "DE",
    "7334956": "ES",
    "7334960": "DE",
    "7334964": "ES",
    "7334996": "DE",
    "7335004": "ES",
    "7335024": "DE",
    "7335032": "ES",
    "7335036": "DE",
    "7335048": "ES",
    "7335078": "DE",
    "7335080": "ES",
    "7335096": "DE",
    "7335104": "ES",
    "7335160": "DE",
    "7335168": "ES",
    "7335936": "CH",
    "7335952": "DE",
    "7336064": "CH",
    "7336072": "DE",
    "7336080": "CH",
    "7336096": "DE",
    "7336112": "CH",
    "7336120": "DE",
    "7336192": "CH",
    "7336232": "DE",
    "7336256": "CH",
    "7336336": "DE",
    "7336352": "CH",
    "7336368": "DE",
    "7336384": "CH",
    "7336400": "DE",
    "7336408": "CH",
    "7336440": "DE",
    "7336480": "CH",
    "7336484": "DE",
    "7336520": "CH",
    "7336528": "DE",
    "7336560": "CH",
    "7336564": "DE",
    "7336572": "CH",
    "7336578": "DE",
    "7336604": "CH",
    "7336608": "DE",
    "7336632": "CH",
    "7336636": "DE",
    "7336644": "CH",
    "7336656": "DE",
    "7336704": "CH",
    "7336768": "DE",
    "7336776": "CH",
    "7336784": "DE",
    "7336800": "CH",
    "7336808": "DE",
    "7336816": "CH",
    "7336824": "DE",
    "7336864": "CH",
    "7336888": "DE",
    "7336912": "CH",
    "7336920": "DE",
    "7336944": "CH",
    "7336960": "BE",
    "7336964": "DE",
    "7336968": "BE",
    "7336972": "DE",
    "7337000": "BE",
    "7337004": "DE",
    "7337012": "BE",
    "7337016": "NL",
    "7337020": "BE",
    "7337024": "DE",
    "7337028": "BE",
    "7337032": "DE",
    "7337036": "BE",
    "7337040": "DE",
    "7337048": "BE",
    "7337056": "DE",
    "7337064": "BE",
    "7337072": "DE",
    "7337076": "BE",
    "7337092": "DE",
    "7337096": "BE",
    "7337100": "DE",
    "7337120": "BE",
    "7337138": "DE",
    "7337140": "BE",
    "7337144": "DE",
    "7337156": "BE",
    "7337160": "DE",
    "7337164": "BE",
    "7337176": "DE",
    "7337192": "BE",
    "7337196": "DE",
    "7337200": "BE",
    "7337208": "DE",
    "7337216": "BE",
    "7337472": "DE",
    "7337496": "IT",
    "7337512": "DE",
    "7337536": "GB",
    "7337544": "DE",
    "7337576": "IT",
    "7337584": "DE",
    "7337592": "IT",
    "7337600": "DE",
    "7337672": "IT",
    "7337680": "DE",
    "7337704": "IT",
    "7337712": "DE",
    "7337728": "IT",
    "7337736": "DE",
    "7337776": "IT",
    "7337784": "DE",
    "7337856": "IT",
    "7337864": "DE",
    "7337872": "IT",
    "7337888": "DE",
    "7337984": "BE",
    "7338004": "DE",
    "7338012": "BE",
    "7338018": "DE",
    "7338020": "BE",
    "7338040": "DE",
    "7338048": "BE",
    "7338064": "DE",
    "7338068": "BE",
    "7338072": "DE",
    "7338080": "BE",
    "7338108": "DE",
    "7338116": "BE",
    "7338120": "DE",
    "7338124": "BE",
    "7338140": "DE",
    "7338148": "BE",
    "7338164": "DE",
    "7338168": "BE",
    "7338184": "DE",
    "7338188": "BE",
    "7338192": "DE",
    "7338196": "BE",
    "7338200": "NL",
    "7338204": "BE",
    "7338224": "DE",
    "7338236": "BE",
    "7338496": "NO",
    "7338508": "SE",
    "7338512": "NO",
    "7338516": "DK",
    "7338520": "NO",
    "7338524": "DK",
    "7338528": "NO",
    "7338532": "DK",
    "7338536": "SE",
    "7338540": "NO",
    "7338544": "DK",
    "7338548": "NO",
    "7338552": "DK",
    "7338556": "NO",
    "7338560": "SE",
    "7338572": "NO",
    "7338576": "DK",
    "7338580": "NO",
    "7338584": "SE",
    "7338588": "DK",
    "7338600": "SE",
    "7338604": "DK",
    "7338616": "NO",
    "7338620": "SE",
    "7338624": "NO",
    "7338632": "DE",
    "7338640": "DK",
    "7338672": "SE",
    "7338680": "DK",
    "7338704": "NO",
    "7338720": "DK",
    "7338728": "SE",
    "7338736": "DK",
    "7338792": "SE",
    "7338800": "NO",
    "7338816": "SE",
    "7338824": "DK",
    "7338864": "SE",
    "7338880": "DK",
    "7338888": "NO",
    "7338912": "DK",
    "7338944": "SE",
    "7338952": "DK",
    "7338960": "NO",
    "7338968": "SE",
    "7338976": "DK",
    "7338984": "SE",
    "7338992": "NO",
    "7339000": "DK",
    "7339008": "BE",
    "7339680": "NL",
    "7339696": "BE",
    "7340032": "RU",
    "7352320": "FR",
    "7360512": "GB",
    "7364608": "IT",
    "7368704": "NL",
    "7372800": "HU",
    "7376896": "IE",
    "7377152": "DE",
    "7377920": "IE",
    "7378432": "DE",
    "7379016": "IE",
    "7379024": "DE",
    "7379136": "IE",
    "7379168": "DE",
    "7380992": "CZ",
    "7385088": "BE",
    "7389184": "FI",
    "7393280": "UA",
    "7397376": "FR",
    "7401472": "FI",
    "7405568": "AM",
    "7411200": "DE",
    "7411712": "AM",
    "7412224": "SG",
    "7412227": "IT",
    "7412228": "SG",
    "7412736": "AM",
    "7413760": "DE",
    "7417856": "LV",
    "7418112": "HU",
    "7419392": "DE",
    "7419904": "HU",
    "7421952": "BE",
    "7424768": "GA",
    "7425024": "ZM",
    "7425152": "GA",
    "7425184": "ZM",
    "7425280": "BE",
    "7428352": "CD",
    "7428608": "BE",
    "7430144": "AT",
    "7434240": "RU",
    "7438336": "PL",
    "7446528": "GB",
    "7450624": "DE",
    "7454720": "FR",
    "7458816": "IT",
    "7462912": "PL",
    "7467008": "ES",
    "7471104": "RU",
    "7479296": "US",
    "7479552": "NL",
    "7479808": "PL",
    "7480064": "US",
    "7480320": "NL",
    "7480576": "ES",
    "7480832": "US",
    "7481088": "CA",
    "7481344": "IR",
    "7481600": "GB",
    "7481856": "RU",
    "7482368": "ES",
    "7482624": "PL",
    "7482880": "IR",
    "7483136": "US",
    "7483392": "GB",
    "7487488": "DE",
    "7491584": "SE",
    "7495680": "NL",
    "7499776": "US",
    "7503872": "ES",
    "7507968": "RU",
    "7512064": "NL",
    "7512096": "IE",
    "7512128": "NL",
    "7516160": "RU",
    "7520256": "US",
    "7522304": "FR",
    "7524352": "DE",
    "7528448": "RU",
    "7536640": "DE",
    "7540736": "IT",
    "7544832": "SE",
    "7553024": "DE",
    "7553792": "",
    "7554048": "DE",
    "7557120": "RU",
    "7561216": "UA",
    "7565312": "IE",
    "7569408": "DE",
    "7572736": "FR",
    "7572992": "DE",
    "7577600": "FR",
    "7581696": "RU",
    "7585792": "NL",
    "7589888": "RO",
    "7593984": "NL",
    "7598080": "CZ",
    "7602176": "ES",
    "7610368": "HU",
    "7614464": "RU",
    "7618560": "AT",
    "7622656": "NO",
    "7626752": "PL",
    "7630848": "DE",
    "7634944": "RU",
    "7643136": "FI",
    "7647232": "AT",
    "7651328": "TR",
    "7655424": "DK",
    "7667712": "NG",
    "7671808": "LT",
    "7675904": "BE",
    "7684096": "UA",
    "7688192": "RU",
    "7692288": "DE",
    "7696384": "RU",
    "7700480": "PL",
    "7704576": "FR",
    "7708672": "US",
    "7712768": "RU",
    "7716864": "LU",
    "7720960": "CZ",
    "7725056": "NL",
    "7729152": "RU",
    "7733248": "IT",
    "7737344": "FR",
    "7741440": "NO",
    "7749632": "RU",
    "7757824": "SK",
    "7761920": "ES",
    "7766016": "GB",
    "7770112": "IT",
    "7774208": "NL",
    "7778304": "RU",
    "7782400": "CH",
    "7786496": "SE",
    "7790592": "FR",
    "7794688": "IT",
    "7798784": "NL",
    "7802880": "RU",
    "7806976": "FI",
    "7811072": "DE",
    "7815168": "PL",
    "7819264": "RU",
    "7823360": "HK",
    "7827456": "SK",
    "7831552": "GB",
    "7831808": "RU",
    "7832064": "DE",
    "7832320": "NL",
    "7833088": "TR",
    "7833344": "US",
    "7833600": "BE",
    "7833856": "GB",
    "7834112": "NL",
    "7834368": "KZ",
    "7834624": "GB",
    "7834880": "ES",
    "7835136": "FR",
    "7835392": "NL",
    "7835648": "CH",
    "7839744": "SE",
    "7843840": "FR",
    "7847936": "DE",
    "7856128": "NL",
    "7860224": "RS",
    "7864320": "NL",
    "7987968": "DE",
    "7988224": "NL",
    "8089949": "US",
    "8089950": "NL",
    "8091356": "US",
    "8091357": "NL",
    "8091358": "US",
    "8091359": "NL",
    "8093132": "US",
    "8093133": "NL",
    "8116992": "DE",
    "8117248": "NL",
    "8126464": "ES",
    "8388608": "FR",
    "8454144": "PT",
    "8519680": "ES",
    "8585216": "TR",
    "8650752": "IL",
    "8716288": "IT",
    "8781824": "GB",
    "8912896": "BE",
    "8978432": "GB",
    "9093120": "HU",
    "9093376": "AE",
    "9093632": "DE",
    "9093690": "RU",
    "9093691": "DE",
    "9093888": "GB",
    "9094400": "IT",
    "9094656": "US",
    "9094912": "CZ",
    "9095168": "CA",
    "9095424": "SG",
    "9095552": "ZA",
    "9095584": "KH",
    "9095616": "PH",
    "9095648": "VN",
    "9095680": "BG",
    "9095904": "TR",
    "9095936": "CH",
    "9096192": "AU",
    "9096704": "US",
    "9096960": "FR",
    "9097216": "US",
    "9097472": "PL",
    "9097728": "GB",
    "9097984": "BE",
    "9098240": "JP",
    "9098496": "CA",
    "9098752": "DE",
    "9099008": "NL",
    "9099264": "DE",
    "9099520": "US",
    "9099776": "ES",
    "9100032": "IT",
    "9100288": "CZ",
    "9100544": "BG",
    "9100737": "TR",
    "9100768": "BG",
    "9100800": "IE",
    "9101056": "GB",
    "9108480": "JP",
    "9108736": "GB",
    "9109248": "US",
    "9109504": "EG",
    "9175040": "GB",
    "9175296": "",
    "9175552": "GB",
    "9191424": "DE",
    "9199616": "US",
    "9201864": "JP",
    "9201865": "US",
    "9202688": "SG",
    "9202944": "GB",
    "9203200": "US",
    "9203712": "SE",
    "9207808": "FI",
    "9240576": "IT",
    "9306112": "SE",
    "9371648": "US",
    "9437184": "JO",
    "9441280": "SK",
    "9445376": "DE",
    "9449472": "HU",
    "9450496": "US",
    "9450752": "HU",
    "9451264": "US",
    "9451520": "HU",
    "9451776": "US",
    "9452800": "HU",
    "9453568": "NO",
    "9457664": "GB",
    "9461760": "RU",
    "9463296": "NL",
    "9463552": "RU",
    "9463808": "IR",
    "9464832": "US",
    "9465856": "FR",
    "9469952": "DE",
    "9474048": "GB",
    "9478144": "RU",
    "9486336": "PL",
    "9494528": "NO",
    "9502720": "MT",
    "9506816": "RU",
    "9510912": "BE",
    "9515008": "DK",
    "9519104": "GB",
    "9523200": "BG",
    "9527296": "DE",
    "9531392": "GB",
    "9539584": "RU",
    "9543680": "BG",
    "9547776": "ES",
    "9551872": "SK",
    "9555968": "LV",
    "9560064": "BR",
    "9561088": "IQ",
    "9562112": "NO",
    "9563136": "HK",
    "9563392": "NL",
    "9563648": "SE",
    "9563817": "GB",
    "9563818": "SE",
    "9563904": "US",
    "9564160": "SA",
    "9568256": "TH",
    "9568512": "ES",
    "9568768": "UA",
    "9569024": "DE",
    "9569280": "HU",
    "9569536": "BR",
    "9569792": "TR",
    "9570304": "RS",
    "9570560": "SG",
    "9570816": "IN",
    "9571584": "PL",
    "9571840": "PT",
    "9572096": "AR",
    "9572352": "AT",
    "9573120": "BG",
    "9573376": "DE",
    "9573632": "LU",
    "9573888": "DE",
    "9574656": "AT",
    "9575424": "AR",
    "9575680": "GB",
    "9575936": "DE",
    "9576192": "SE",
    "9576448": "RU",
    "9580544": "CH",
    "9584640": "EE",
    "9588736": "GB",
    "9590528": "NL",
    "9590784": "GB",
    "9601024": "DE",
    "9609216": "CH",
    "9613312": "IE",
    "9617408": "IT",
    "9621504": "IR",
    "9625600": "FR",
    "9629696": "UA",
    "9633792": "PS",
    "9634816": "SE",
    "9635840": "UA",
    "9636864": "LT",
    "9637888": "RU",
    "9641984": "LT",
    "9646080": "DE",
    "9654272": "GB",
    "9658368": "DE",
    "9660416": "",
    "9660672": "DE",
    "9662464": "GI",
    "9666560": "IT",
    "9674752": "UA",
    "9677824": "PL",
    "9678080": "UA",
    "9678848": "US",
    "9679360": "HK",
    "9679872": "DE",
    "9680384": "KR",
    "9680896": "US",
    "9682944": "FR",
    "9687040": "CH",
    "9691136": "GE",
    "9695232": "GB",
    "9696393": "DE",
    "9696394": "GB",
    "9699328": "CH",
    "9703424": "NL",
    "9707520": "GB",
    "9711616": "RU",
    "9715712": "ES",
    "9719808": "NL",
    "9723904": "IT",
    "9732096": "DE",
    "9733120": "NL",
    "9734144": "ES",
    "9735168": "US",
    "9736192": "NO",
    "9740288": "NL",
    "9748480": "RU",
    "9756672": "DE",
    "9760768": "GB",
    "9764864": "ES",
    "9768960": "RU",
    "9773056": "NL",
    "9773843": "",
    "9773844": "NL",
    "9776128": "",
    "9776384": "NL",
    "9777152": "FI",
    "9781248": "NL",
    "9785344": "IT",
    "9789440": "GB",
    "9791488": "US",
    "9793536": "NO",
    "9797632": "NL",
    "9801728": "ES",
    "9805824": "AT",
    "9809920": "RU",
    "9814016": "NL",
    "9822208": "AT",
    "9826304": "PL",
    "9830400": "RU",
    "9846784": "SE",
    "9848832": "RU",
    "9850880": "LB",
    "9852928": "NL",
    "9854976": "GB",
    "9863168": "HU",
    "9867264": "DE",
    "9871360": "SE",
    "9879058": "NL",
    "9879059": "SE",
    "9879552": "RU",
    "9883648": "ES",
    "9887744": "CH",
    "9895936": "FR",
    "9900032": "RU",
    "9904128": "HK",
    "9905408": "GB",
    "9905536": "HK",
    "9906710": "DE",
    "9906711": "HK",
    "9906780": "BE",
    "9906784": "HK",
    "9906804": "BE",
    "9906808": "HK",
    "9906818": "DE",
    "9906819": "HK",
    "9906822": "GB",
    "9906823": "HK",
    "9906830": "SE",
    "9906831": "HK",
    "9906834": "GB",
    "9906835": "HK",
    "9906838": "CH",
    "9906839": "HK",
    "9906846": "FR",
    "9906847": "HK",
    "9906850": "AT",
    "9906851": "HK",
    "9906854": "TR",
    "9906855": "HK",
    "9906870": "IT",
    "9906871": "HK",
    "9906912": "GB",
    "9906920": "HK",
    "9908224": "SE",
    "9912320": "RU",
    "9916416": "DE",
    "9919232": "AT",
    "9919296": "DE",
    "9920512": "NO",
    "9920768": "GB",
    "9924608": "CH",
    "9928704": "RU",
    "9932800": "DE",
    "9936896": "IS",
    "9945088": "SE",
    "9949184": "DE",
    "9953280": "RU",
    "9954560": "PL",
    "9954816": "KZ",
    "9955072": "PL",
    "9955328": "RU",
    "9957376": "DE",
    "9960448": "RU",
    "9960451": "DE",
    "9960704": "PL",
    "9960707": "DE",
    "9961472": "FI",
    "10027008": "PL",
    "10092544": "GB",
    "10223616": "RO",
    "10227968": "BE",
    "10228224": "RO",
    "10236160": "JP",
    "10236416": "IT",
    "10236672": "RO",
    "10256384": "GB",
    "10258440": "IT",
    "10258448": "GB",
    "10258496": "FI",
    "10258528": "GB",
    "10258544": "NO",
    "10258552": "GB",
    "10260064": "DZ",
    "10260072": "BE",
    "10260088": "GR",
    "10260096": "GB",
    "10260522": "FR",
    "10260523": "GB",
    "10260576": "GR",
    "10260584": "GB",
    "10260592": "RS",
    "10260608": "GB",
    "10260672": "MA",
    "10260680": "NO",
    "10260688": "CZ",
    "10260696": "GB",
    "10260704": "IL",
    "10260712": "GB",
    "10260720": "LT",
    "10260728": "GB",
    "10261600": "ES",
    "10261608": "GB",
    "10261616": "RO",
    "10261632": "GB",
    "10262832": "FR",
    "10262840": "GB",
    "10262896": "LV",
    "10262904": "GB",
    "10263936": "BG",
    "10263952": "GB",
    "10264248": "DZ",
    "10264256": "GB",
    "10265024": "GR",
    "10265056": "GB",
    "10265216": "GR",
    "10265344": "GB",
    "10265518": "IL",
    "10265519": "GB",
    "10265640": "FR",
    "10265648": "GB",
    "10266928": "FR",
    "10266944": "GB",
    "10267560": "FR",
    "10267568": "GB",
    "10267648": "SE",
    "10267944": "DE",
    "10267952": "SE",
    "10267968": "GB",
    "10267976": "SE",
    "10267992": "RO",
    "10268008": "SE",
    "10268152": "LV",
    "10268160": "GB",
    "10273960": "DK",
    "10273968": "BE",
    "10273976": "FR",
    "10273984": "DE",
    "10273992": "JE",
    "10274000": "NL",
    "10274008": "IT",
    "10274016": "LU",
    "10274024": "ES",
    "10274032": "SE",
    "10274040": "CH",
    "10274048": "GB",
    "10275264": "RU",
    "10275272": "GB",
    "10275304": "RU",
    "10275312": "GB",
    "10275648": "AT",
    "10275656": "GB",
    "10277010": "DE",
    "10277011": "GB",
    "10277016": "HU",
    "10277024": "GB",
    "10277072": "IT",
    "10277104": "GB",
    "10277112": "BE",
    "10277120": "GB",
    "10277752": "BE",
    "10277760": "GB",
    "10277936": "NL",
    "10277952": "GB",
    "10278040": "ES",
    "10278048": "GB",
    "10278072": "ES",
    "10278080": "GB",
    "10279624": "BE",
    "10279632": "GB",
    "10280680": "GR",
    "10280688": "GB",
    "10283336": "IL",
    "10283344": "GB",
    "10283552": "CH",
    "10283568": "GB",
    "10283576": "DE",
    "10283592": "GB",
    "10283736": "TR",
    "10283744": "GB",
    "10284568": "DK",
    "10284584": "PL",
    "10284600": "GB",
    "10284752": "LT",
    "10284760": "GB",
    "10284768": "EE",
    "10284784": "GB",
    "10288200": "SA",
    "10288216": "CZ",
    "10288224": "NL",
    "10288232": "GB",
    "10288256": "NL",
    "10288264": "GB",
    "10288280": "RU",
    "10288296": "GB",
    "10288304": "GR",
    "10288312": "GB",
    "10288320": "FI",
    "10288328": "GB",
    "10288376": "FI",
    "10288384": "GB",
    "10288992": "HU",
    "10289000": "JO",
    "10289008": "GB",
    "10289016": "NO",
    "10289024": "GB",
    "10289152": "DK",
    "10354688": "GB",
    "10420224": "US",
    "10452992": "EE",
    "10485760": "DE",
    "10493952": "ES",
    "10494208": "DE",
    "10495744": "ES",
    "10496000": "DE",
    "10551296": "GB",
    "10571776": "IE",
    "10572056": "DE",
    "10572060": "IE",
    "10572800": "GB",
    "10576365": "PL",
    "10576366": "GB",
    "10577747": "PL",
    "10577748": "GB",
    "10616832": "CH",
    "10682368": "GB",
    "10685126": "AU",
    "10685127": "GB",
    "10688256": "DE",
    "10688512": "GB",
    "10689024": "IT",
    "10689280": "GB",
    "10689536": "DE",
    "10690304": "GB",
    "10694912": "",
    "10695168": "GB",
    "10696960": "FR",
    "10697728": "GB",
    "10702848": "FR",
    "10706123": "PT",
    "10706124": "FR",
    "10706944": "GB",
    "10710280": "IT",
    "10710296": "GB",
    "10710508": "CH",
    "10710512": "GB",
    "10715136": "IE",
    "10716160": "GB",
    "10718214": "AE",
    "10718215": "GB",
    "10718242": "AE",
    "10718243": "GB",
    "10719273": "IT",
    "10719274": "GB",
    "10719424": "ES",
    "10719432": "GB",
    "10747904": "AE",
    "10878976": "NL",
    "10899456": "BE",
    "10900480": "NL",
    "10944512": "FR",
    "11010048": "ES",
    "11014144": "GB",
    "11018240": "CH",
    "11026432": "RU",
    "11030528": "NO",
    "11034624": "FR",
    "11038720": "PT",
    "11040768": "BE",
    "11042816": "PL",
    "11046912": "GB",
    "11051008": "MT",
    "11055104": "AZ",
    "11059200": "PL",
    "11063296": "CZ",
    "11067392": "CH",
    "11067904": "IT",
    "11069184": "CH",
    "11069440": "IT",
    "11071488": "RU",
    "11073536": "GB",
    "11091968": "FI",
    "11096064": "RU",
    "11100160": "IT",
    "11108352": "CH",
    "11116544": "GB",
    "11120640": "CZ",
    "11124736": "TR",
    "11128832": "RS",
    "11132928": "NL",
    "11137024": "FR",
    "11141120": "NL",
    "11149312": "SA",
    "11157504": "RU",
    "11165696": "CZ",
    "11169792": "RU",
    "11173888": "NO",
    "11177984": "ML",
    "11182080": "PL",
    "11186176": "DE",
    "11190272": "NO",
    "11194368": "RU",
    "11198464": "IT",
    "11202560": "IR",
    "11206656": "RU",
    "11210752": "FR",
    "11214848": "IT",
    "11218944": "PL",
    "11223040": "IT",
    "11227136": "CD",
    "11231232": "GB",
    "11235328": "DE",
    "11239424": "GB",
    "11243520": "KZ",
    "11243776": "IR",
    "11244032": "RU",
    "11244544": "IR",
    "11245568": "RU",
    "11247616": "IT",
    "11251712": "LU",
    "11255808": "NO",
    "11259904": "IS",
    "11264000": "NL",
    "11266048": "IT",
    "11268096": "DE",
    "11272192": "IT",
    "11276288": "RU",
    "11280384": "DE",
    "11288576": "ES",
    "11292672": "FO",
    "11296768": "IR",
    "11304960": "GB",
    "11309056": "SK",
    "11313152": "FR",
    "11313664": "DE",
    "11314176": "FR",
    "11314432": "DE",
    "11315200": "US",
    "11315712": "FR",
    "11316480": "DE",
    "11317248": "FR",
    "11321088": "DE",
    "11321344": "IT",
    "11329536": "PL",
    "11341824": "RU",
    "11345920": "HU",
    "11350016": "GB",
    "11354112": "RU",
    "11358208": "SA",
    "11362304": "IE",
    "11362316": "GB",
    "11362320": "IE",
    "11362444": "GB",
    "11362448": "IE",
    "11362636": "GB",
    "11362640": "IE",
    "11364336": "GB",
    "11364340": "IE",
    "11364488": "GB",
    "11364492": "IE",
    "11364560": "GB",
    "11364568": "IE",
    "11365120": "AT",
    "11365328": "BE",
    "11365336": "AT",
    "11365376": "IE",
    "11366400": "ES",
    "11370496": "DE",
    "11378688": "PL",
    "11390976": "UA",
    "11395072": "LI",
    "11399168": "NO",
    "11403264": "RU",
    "11407360": "IR",
    "11411456": "TR",
    "11415552": "BG",
    "11419648": "SE",
    "11427840": "RU",
    "11431936": "IT",
    "11440128": "BG",
    "11444224": "RU",
    "11452416": "FR",
    "11460608": "TM",
    "11464704": "GB",
    "11468800": "RU",
    "11481088": "IT",
    "11485184": "GB",
    "11488000": "",
    "11488256": "GB",
    "11489280": "IL",
    "11493376": "DE",
    "11497472": "SE",
    "11501568": "RU",
    "11509760": "MQ",
    "11517952": "AT",
    "11522048": "CY",
    "11526144": "DE",
    "11530496": "TH",
    "11530752": "DE",
    "11531008": "TH",
    "11531264": "DE",
    "11534336": "GB",
    "11665408": "JP",
    "11730944": "GB",
    "11829248": "FR",
    "11845632": "US",
    "11862016": "GB",
    "11894784": "FR",
    "11925504": "BE",
    "11925760": "FR",
    "11926016": "DE",
    "11926528": "BE",
    "11927552": "FR",
    "11927564": "DE",
    "11927568": "FR",
    "11927616": "NL",
    "11927632": "FR",
    "11927744": "DE",
    "11927745": "FR",
    "11928983": "IT",
    "11928984": "FR",
    "11929088": "ES",
    "11929152": "FR",
    "11929216": "ES",
    "11929280": "FR",
    "11930112": "ES",
    "11930176": "FR",
    "11933312": "ES",
    "11933344": "FR",
    "11933984": "DE",
    "11933992": "FR",
    "11934912": "ES",
    "11934976": "FR",
    "11937536": "ES",
    "11937600": "FR",
    "11938176": "ES",
    "11938304": "FR",
    "11940068": "GB",
    "11940072": "FR",
    "11943698": "PT",
    "11943699": "FR",
    "11943920": "BE",
    "11943936": "FR",
    "11946496": "PL",
    "11946752": "FR",
    "11946951": "PL",
    "11946952": "FR",
    "11947655": "PL",
    "11947656": "FR",
    "11947680": "PL",
    "11947712": "FR",
    "11947969": "PL",
    "11947970": "FR",
    "11952384": "GB",
    "11952640": "FR",
    "11952768": "GB",
    "11952896": "FR",
    "11954048": "ES",
    "11954112": "FR",
    "11956352": "ES",
    "11956416": "FR",
    "11958720": "ES",
    "11958784": "FR",
    "11965504": "ES",
    "11965568": "FR",
    "11966080": "ES",
    "11966208": "FR",
    "11973872": "ES",
    "11973888": "FR",
    "11974272": "ES",
    "11974400": "FR",
    "11977728": "DE",
    "11978752": "FR",
    "11979008": "PL",
    "11979264": "FR",
    "11982784": "ES",
    "11982848": "FR",
    "11983400": "ES",
    "11983408": "FR",
    "11984368": "DE",
    "11984376": "FR",
    "11984704": "GB",
    "11984832": "FR",
    "11984896": "ES",
    "11984960": "FR",
    "11985024": "DE",
    "11985040": "FR",
    "11985856": "GB",
    "11985920": "FR",
    "11986496": "GB",
    "11986560": "FR",
    "11987504": "ES",
    "11987508": "FR",
    "11987712": "ES",
    "11987776": "FR",
    "11991328": "GB",
    "11991360": "FR",
    "11993088": "IE",
    "12058624": "DE",
    "12582912": "CH",
    "12713984": "IT",
    "12718080": "NL",
    "12722176": "DE",
    "12722803": "",
    "12722804": "DE",
    "12726272": "CH",
    "12730368": "DE",
    "12734464": "FR",
    "12738560": "NL",
    "12746752": "AT",
    "12747264": "CA",
    "12747776": "AT",
    "12748800": "CA",
    "12749312": "AT",
    "12749568": "CA",
    "12749824": "AT",
    "12750686": "GN",
    "12750687": "AT",
    "12750746": "GN",
    "12750747": "AT",
    "12750848": "CA",
    "12751104": "AT",
    "12751872": "NL",
    "12752128": "AT",
    "12752384": "CA",
    "12753152": "NL",
    "12753408": "AT",
    "12754176": "IL",
    "12754432": "AT",
    "12754944": "CZ",
    "12759040": "IT",
    "12763136": "IL",
    "12767232": "GB",
    "12771328": "DE",
    "12775424": "RU",
    "12779520": "DE",
    "12783616": "FR",
    "12787712": "DE",
    "12791808": "LV",
    "12795904": "RU",
    "12808192": "NL",
    "12812288": "GR",
    "12816384": "GB",
    "12816640": "NL",
    "12816896": "IN",
    "12817408": "DE",
    "12818432": "NL",
    "12819456": "DE",
    "12820480": "CZ",
    "12824576": "DK",
    "12828672": "TR",
    "12828928": "LU",
    "12829184": "DE",
    "12829440": "TR",
    "12830720": "AE",
    "12830976": "LU",
    "12831232": "TR",
    "12832000": "US",
    "12832256": "TR",
    "12832768": "RU",
    "12836864": "US",
    "12845056": "GB",
    "12849152": "KZ",
    "12853248": "BE",
    "12857344": "NO",
    "12861440": "AT",
    "12869632": "RU",
    "12870400": "FI",
    "12870656": "RU",
    "12873728": "CZ",
    "12877824": "IT",
    "12881920": "AT",
    "12886016": "UA",
    "12890112": "CH",
    "12894208": "MK",
    "12898304": "CZ",
    "12902400": "GB",
    "12910592": "RU",
    "12914688": "ES",
    "12918784": "CZ",
    "12922880": "SE",
    "12926976": "PL",
    "12931072": "DE",
    "12935168": "GB",
    "12935424": "CA",
    "12935680": "RO",
    "12936192": "IT",
    "12936448": "CH",
    "12936704": "PL",
    "12936960": "MD",
    "12937216": "CY",
    "12937472": "TJ",
    "12937728": "IT",
    "12937984": "RU",
    "12938240": "FR",
    "12939008": "ES",
    "12939264": "RU",
    "12943360": "CH",
    "12945408": "BA",
    "12947456": "CZ",
    "12951552": "SG",
    "12952064": "NL",
    "12952320": "US",
    "12952576": "NO",
    "12953600": "US",
    "12954112": "ID",
    "12954368": "US",
    "12954624": "UA",
    "12955648": "HU",
    "12959744": "RU",
    "12963840": "CH",
    "12967936": "RU",
    "12980224": "NL",
    "12984320": "GB",
    "12992512": "SE",
    "12996608": "RU",
    "13000704": "GB",
    "13004800": "CZ",
    "13008896": "IT",
    "13012992": "SE",
    "13017088": "RU",
    "13021184": "UA",
    "13021440": "RO",
    "13021696": "UA",
    "13022976": "GB",
    "13023232": "FR",
    "13023488": "DE",
    "13023744": "MT",
    "13024000": "AT",
    "13024512": "DE",
    "13024768": "IR",
    "13025024": "SG",
    "13025280": "ES",
    "13029376": "DK",
    "13033472": "LV",
    "13037568": "DE",
    "13041664": "IT",
    "13049856": "NO",
    "13052460": "FI",
    "13052461": "NO",
    "13058048": "DE",
    "13062144": "AT",
    "13066240": "LV",
    "13074432": "BA",
    "13078528": "KE",
    "13082624": "GB",
    "13090816": "DE",
    "13094912": "RU",
    "13099008": "UA",
    "13103104": "RU",
    "13107200": "IT",
    "13369344": "GB",
    "13631488": "SE",
    "13643776": "NO",
    "13643904": "SE",
    "13644032": "NO",
    "13644288": "SE",
    "13674496": "NO",
    "13675264": "SE",
    "13847808": "NO",
    "13847936": "SE",
    "13951142": "FI",
    "13951144": "SE",
    "13951148": "FI",
    "13951152": "SE",
    "13951156": "FI",
    "13951160": "SE",
    "13951164": "FI",
    "13951166": "SE",
    "13952533": "NO",
    "13952534": "SE",
    "13954860": "FR",
    "13954878": "SE",
    "13954909": "FR",
    "13954923": "SE",
    "13954924": "FR",
    "13954926": "SE",
    "13955136": "IT",
    "13955168": "SE",
    "13956160": "ES",
    "13956192": "SE",
    "13956416": "CH",
    "13956448": "SE",
    "13957200": "FR",
    "13957216": "SE",
    "13958176": "GB",
    "13958192": "SE",
    "13958250": "FI",
    "13958254": "SE",
    "13958258": "FI",
    "13958262": "SE",
    "13958266": "FI",
    "13958267": "SE",
    "13958348": "FI",
    "13958352": "SE",
    "13958356": "FI",
    "13958360": "SE",
    "13958364": "FI",
    "13958368": "SE",
    "13958372": "FI",
    "13958376": "SE",
    "13958380": "FI",
    "13958381": "SE",
    "14155776": "ES",
    "14286848": "IR",
    "14417920": "IT",
    "14680064": "DE"
}