{
    "0": "US",
    "524288": "US",
    "786432": "US",
    "917504": "US",
    "918016": "CA",
    "918024": "CA",
    "918028": "US",
    "918032": "CA",
    "918048": "CA",
    "918080": "CA",
    "918144": "CA",
    "918176": "CA",
    "918192": "CA",
    "918196": "CA",
    "918198": "US",
    "918199": "CA",
    "918200": "CA",
    "918208": "CA",
    "918272": "CA",
    "918528": "US",
    "919552": "US",
    "921600": "US",
    "925696": "US",
    "933888": "US",
    "950272": "US",
    "983040": "US",
    "1048576": "US",
    "1056768": "US",
    "1060864": "CA",
    "1062912": "US",
    "1064960": "US",
    "1081344": "US",
    "1114112": "US",
    "1179648": "US",
    "1310720": "US",
    "1572864": "US",
    "1835008": "US",
    "1867776": "CA",
    "1871872": "US",
    "1875968": "US",
    "1884160": "US",
    "1900544": "US",
    "1966080": "US",
    "2031616": "US",
    "2064384": "US",
    "2066432": "US",
    "2066944": "US",
    "2067200": "CA",
    "2067456": "US",
    "2068480": "US",
    "2072576": "US",
    "2080768": "US",
    "2097152": "US",
    "2162688": "US",
    "2195456": "US",
    "2211840": "GB",
    "2215936": "GB",
    "2217984": "GB",
    "2219008": "AR",
    "2220032": "BR",
    "2221056": "US",
    "2222080": "CO",
    "2222592": "US",
    "2223104": "US",
    "2224128": "US",
    "2228224": "US",
    "2359296": "US",
    "2621440": "US",
    "3145728": "US",
    "3670016": "US",
    "3801088": "US",
    "3866624": "US",
    "3899392": "US",
    "3907584": "US",
    "3911680": "CA",
    "3913728": "US",
    "3915776": "US",
    "3923968": "US",
    "3926016": "US",
    "3926528": "US",
    "3926592": "CA",
    "3926600": "US",
    "3926608": "US",
    "3926616": "US",
    "3926620": "CA",
    "3926624": "US",
    "3926656": "US",
    "3926784": "US",
    "3927040": "US",
    "3928064": "US",
    "3932160": "US",
    "4194304": "US",
    "4456448": "US",
    "4521984": "US",
    "4554752": "US",
    "4558848": "US",
    "4560896": "US",
    "4561152": "US",
    "4561280": "US",
    "4561344": "US",
    "4561345": "NL",
    "4561346": "US",
    "4561348": "US",
    "4561352": "US",
    "4561360": "US",
    "4561376": "US",
    "4561408": "US",
    "4561920": "US",
    "4562944": "US",
    "4571136": "US",
    "4587520": "US",
    "4653056": "US",
    "4685824": "US",
    "4689920": "US",
    "4691968": "US",
    "4692224": "US",
    "4692288": "US",
    "4692320": "US",
    "4692328": "US",
    "4692330": "CA",
    "4692331": "US",
    "4692332": "US",
    "4692336": "US",
    "4692352": "US",
    "4692480": "US",
    "4692992": "US",
    "4694016": "US",
    "4702208": "US",
    "4718592": "US",
    "4980736": "US",
    "5111808": "US",
    "5120000": "US",
    "5124096": "US",
    "5125120": "US",
    "5125152": "US",
    "5125168": "CA",
    "5125184": "US",
    "5125248": "US",
    "5125376": "US",
    "5125632": "US",
    "5126144": "US",
    "5128192": "US",
    "5144576": "US",
    "5177344": "US",
    "5242880": "US",
    "6291456": "US",
    "8388608": "US"
}