{
    "0": "GB",
    "524288": "RE",
    "573440": "FR",
    "671744": "JO",
    "675840": "FR",
    "781770": "RE",
    "781771": "FR",
    "803132": "RE",
    "803133": "FR",
    "811156": "US",
    "811160": "FR",
    "811164": "US",
    "811168": "FR",
    "811172": "US",
    "811176": "FR",
    "811180": "US",
    "811184": "FR",
    "811188": "US",
    "811192": "FR",
    "811196": "US",
    "811200": "FR",
    "811204": "US",
    "811207": "FR",
    "811212": "US",
    "811216": "FR",
    "811244": "US",
    "811245": "FR",
    "811246": "US",
    "811248": "FR",
    "811252": "US",
    "811253": "FR",
    "811734": "US",
    "811736": "FR",
    "840704": "RE",
    "841216": "FR",
    "847872": "RE",
    "848384": "FR",
    "848640": "RE",
    "848896": "FR",
    "849920": "RE",
    "851968": "FR",
    "1048576": "IT",
    "1572864": "ES",
    "2621440": "GB",
    "3145728": "PL",
    "3227648": "ES",
    "3227649": "PL",
    "3424256": "ES",
    "3424257": "PL",
    "3439099": "ES",
    "3439100": "PL",
    "3670016": "NL",
    "3801088": "ES",
    "3932160": "NL",
    "4063232": "DK",
    "4194304": "FI",
    "4198400": "KZ",
    "4198656": "NL",
    "4198912": "NG",
    "4199168": "BY",
    "4199424": "RU",
    "4201216": "CZ",
    "4201472": "RU",
    "4201984": "RO",
    "4202240": "RU",
    "4202496": "ES",
    "4206592": "GB",
    "4210688": "HU",
    "4214784": "UA",
    "4218880": "RU",
    "4221072": "DE",
    "4221080": "RU",
    "4221408": "DE",
    "4221430": "RU",
    "4221431": "DE",
    "4221440": "RU",
    "4222976": "IT",
    "4227072": "AT",
    "4231168": "LU",
    "4235264": "RU",
    "4239360": "DE",
    "4243456": "NO",
    "4247552": "MT",
    "4248576": "IT",
    "4249600": "GB",
    "4250624": "DE",
    "4251648": "",
    "4251904": "FR",
    "4253696": "NL",
    "4255744": "DE",
    "4256768": "NL",
    "4263424": "ES",
    "4263680": "NL",
    "4263936": "RU",
    "4268032": "NL",
    "4272128": "NO",
    "4274944": "SE",
    "4275200": "NO",
    "4275456": "SE",
    "4275712": "NO",
    "4275968": "SE",
    "4276224": "BA",
    "4284416": "NL",
    "4292608": "BE",
    "4296704": "IT",
    "4300800": "SI",
    "4304384": "BA",
    "4304896": "CZ",
    "4308992": "SE",
    "4313088": "IN",
    "4313344": "OM",
    "4313600": "DE",
    "4313856": "FR",
    "4314112": "PL",
    "4315136": "GB",
    "4316160": "DE",
    "4317184": "FR",
    "4321280": "IM",
    "4325376": "DE",
    "4333568": "AT",
    "4341760": "RU",
    "4342272": "FI",
    "4342528": "RU",
    "4343808": "DE",
    "4344064": "RU",
    "4344832": "DE",
    "4345088": "RU",
    "4345600": "MD",
    "4345856": "RU",
    "4346880": "NL",
    "4347136": "RU",
    "4347648": "DE",
    "4348160": "RU",
    "4349952": "DE",
    "4354048": "ES",
    "4358144": "BE",
    "4358156": "US",
    "4358158": "BE",
    "4358188": "US",
    "4358192": "BE",
    "4358440": "US",
    "4358444": "BE",
    "4358604": "NL",
    "4358608": "BE",
    "4358856": "US",
    "4358864": "BE",
    "4359360": "US",
    "4359392": "BE",
    "4359968": "US",
    "4359976": "BE",
    "4360193": "US",
    "4360195": "BE",
    "4360210": "US",
    "4360211": "BE",
    "4360268": "US",
    "4360270": "BE",
    "4360448": "RO",
    "4360452": "BE",
    "4360456": "US",
    "4360460": "BE",
    "4360488": "PL",
    "4360492": "HR",
    "4360496": "BE",
    "4361152": "US",
    "4361184": "BE",
    "4361728": "US",
    "4361984": "CZ",
    "4361988": "BE",
    "4362240": "RU",
    "4366336": "FI",
    "4370432": "IR",
    "4374528": "DE",
    "4375552": "US",
    "4375808": "NL",
    "4376064": "EE",
    "4376320": "SG",
    "4376576": "GB",
    "4377600": "DE",
    "4378624": "IT",
    "4382720": "LI",
    "4386816": "EE",
    "4390912": "SE",
    "4392704": "NO",
    "4392960": "SE",
    "4395008": "DE",
    "4395264": "FR",
    "4395520": "DE",
    "4395776": "FR",
    "4398336": "DE",
    "4398592": "FR",
    "4398848": "DE",
    "4399104": "BZ",
    "4400128": "NO",
    "4401152": "RU",
    "4402176": "ES",
    "4403200": "RU",
    "4407296": "NL",
    "4407306": "US",
    "4407307": "NL",
    "4407552": "IN",
    "4407808": "IT",
    "4408064": "NL",
    "4408320": "IT",
    "4408576": "NL",
    "4408832": "US",
    "4409088": "NL",
    "4409600": "US",
    "4409856": "NL",
    "4409860": "DE",
    "4409864": "NL",
    "4409868": "DE",
    "4409872": "NL",
    "4409876": "DE",
    "4409880": "NL",
    "4409884": "DE",
    "4409888": "NL",
    "4409892": "DE",
    "4409896": "NL",
    "4409900": "DE",
    "4409904": "NL",
    "4409908": "DE",
    "4409912": "NL",
    "4409916": "DE",
    "4409920": "NL",
    "4409924": "DE",
    "4409928": "NL",
    "4409932": "DE",
    "4409936": "NL",
    "4409940": "DE",
    "4409944": "NL",
    "4409948": "DE",
    "4409952": "NL",
    "4409956": "DE",
    "4409960": "NL",
    "4409964": "DE",
    "4409968": "NL",
    "4409972": "DE",
    "4409976": "NL",
    "4409980": "DE",
    "4409984": "NL",
    "4411904": "CH",
    "4412160": "NL",
    "4415488": "ES",
    "4419584": "IT",
    "4423680": "MU",
    "4427776": "CH",
    "4431872": "FR",
    "4437248": "BE",
    "4437504": "FR",
    "4439808": "BE",
    "4440064": "SE",
    "4444160": "RU",
    "4448256": "DE",
    "4452352": "RU",
    "4460544": "GB",
    "4472832": "RU",
    "4476928": "GB",
    "4481024": "SE",
    "4489216": "ES",
    "4493312": "DE",
    "4493568": "UA",
    "4493824": "PL",
    "4494080": "UA",
    "4494336": "US",
    "4494592": "AT",
    "4494848": "US",
    "4495104": "HU",
    "4495360": "GB",
    "4495616": "SI",
    "4495872": "SE",
    "4496128": "ES",
    "4496384": "PL",
    "4496640": "LU",
    "4496896": "UA",
    "4497152": "CH",
    "4497408": "DE",
    "4501504": "IT",
    "4509696": "GB",
    "4513792": "PL",
    "4517888": "RU",
    "4521984": "GB",
    "4530176": "DE",
    "4534272": "AZ",
    "4538368": "NL",
    "4546560": "DE",
    "4554752": "GB",
    "4558848": "RU",
    "4562944": "FI",
    "4567040": "RU",
    "4571136": "DE",
    "4575232": "RE",
    "4579328": "SE",
    "4583424": "IT",
    "4587520": "DK",
    "4589312": "NO",
    "4589568": "DK",
    "4591616": "LV",
    "4595712": "FR",
    "4599808": "GB",
    "4603904": "UA",
    "4612096": "RU",
    "4616192": "IT",
    "4618240": "SY",
    "4620288": "IL",
    "4624384": "SE",
    "4628480": "DE",
    "4636672": "US",
    "4640768": "FR",
    "4644864": "RU",
    "4648960": "RS",
    "4653056": "GB",
    "4661248": "CA",
    "4662474": "US",
    "4662475": "CA",
    "4665344": "MT",
    "4669440": "DK",
    "4677632": "MT",
    "4681728": "IR",
    "4685824": "DK",
    "4689920": "US",
    "4690176": "TR",
    "4690432": "PL",
    "4690688": "BY",
    "4690944": "US",
    "4691200": "IR",
    "4691456": "US",
    "4692736": "ES",
    "4692992": "RU",
    "4693248": "MD",
    "4693504": "UA",
    "4693760": "US",
    "4694016": "RU",
    "4702208": "FI",
    "4706304": "RU",
    "4710400": "IT",
    "4711168": "NL",
    "4711424": "US",
    "4711680": "IT",
    "4712192": "DE",
    "4712448": "NL",
    "4712704": "HK",
    "4712960": "IT",
    "4713984": "HK",
    "4714240": "IT",
    "4714496": "RU",
    "4718592": "SE",
    "4722688": "RU",
    "4726784": "PL",
    "4730880": "LI",
    "4732711": "CH",
    "4732712": "LI",
    "4732716": "CH",
    "4732717": "LI",
    "4734976": "BG",
    "4738560": "US",
    "4738816": "BG",
    "4743168": "KE",
    "4747264": "RU",
    "4751360": "DE",
    "4755456": "DK",
    "4759552": "IT",
    "4763648": "KG",
    "4767744": "PL",
    "4771840": "RU",
    "4780032": "DE",
    "4784128": "UA",
    "4788224": "RU",
    "4792320": "DE",
    "4796416": "SE",
    "4800512": "RU",
    "4808704": "DE",
    "4816896": "NL",
    "4818432": "US",
    "4818688": "SE",
    "4818944": "NL",
    "4820992": "ES",
    "4825088": "RU",
    "4829184": "SE",
    "4833280": "RU",
    "4837376": "FK",
    "4840192": "GB",
    "4841472": "IT",
    "4845568": "TJ",
    "4845824": "FR",
    "4846080": "US",
    "4846336": "BR",
    "4846592": "US",
    "4846848": "PL",
    "4847104": "NL",
    "4847616": "GB",
    "4853760": "FR",
    "4855808": "NL",
    "4857856": "CZ",
    "4861952": "DE",
    "4866048": "FR",
    "4870144": "SA",
    "4874240": "IL",
    "4882432": "CH",
    "4890624": "RS",
    "4894720": "IT",
    "4898816": "FI",
    "4907008": "GB",
    "4915200": "IR",
    "4919296": "DE",
    "4921344": "IT",
    "4923392": "AT",
    "4931584": "GB",
    "4935680": "RU",
    "4939776": "FI",
    "4943872": "CH",
    "4947968": "RU",
    "4952064": "FR",
    "4956160": "EG",
    "4964352": "CH",
    "4968448": "DK",
    "4968704": "GB",
    "4968960": "DE",
    "4969728": "IR",
    "4969984": "DE",
    "4970240": "BG",
    "4970496": "NL",
    "4970752": "DE",
    "4971008": "GB",
    "4971520": "DE",
    "4971776": "BR",
    "4972032": "NL",
    "4972288": "RU",
    "4972544": "AT",
    "4980736": "CH",
    "4982656": "AT",
    "4982784": "ES",
    "4984832": "IT",
    "4988928": "DE",
    "4989440": "NL",
    "4989952": "DE",
    "4990976": "RU",
    "4991744": "DE",
    "4992000": "US",
    "4993536": "IQ",
    "4993792": "DE",
    "4994048": "ID",
    "4995072": "GB",
    "4996096": "RU",
    "4996608": "GB",
    "4996864": "RU",
    "4997120": "IT",
    "5005312": "RU",
    "5009408": "GB",
    "5013504": "RU",
    "5017600": "SE",
    "5021696": "QA",
    "5025792": "RU",
    "5029888": "GB",
    "5038080": "RU",
    "5046272": "GB",
    "5050368": "DE",
    "5052160": "GB",
    "5052416": "DE",
    "5052672": "EE",
    "5052928": "DE",
    "5054464": "UA",
    "5058560": "GE",
    "5062656": "DK",
    "5062659": "US",
    "5062660": "DK",
    "5063056": "US",
    "5063060": "DK",
    "5063168": "US",
    "5063176": "DK",
    "5063184": "US",
    "5063192": "DK",
    "5063456": "US",
    "5063472": "DK",
    "5066752": "US",
    "5070848": "SE",
    "5074944": "HU",
    "5079040": "FO",
    "5083136": "MK",
    "5087232": "RU",
    "5091328": "LB",
    "5095424": "MT",
    "5099520": "DE",
    "5103616": "FR",
    "5107712": "US",
    "5107968": "GB",
    "5108224": "US",
    "5108480": "GB",
    "5108736": "US",
    "5111808": "FR",
    "5115904": "SE",
    "5120000": "UA",
    "5128192": "AL",
    "5132288": "DE",
    "5136384": "RU",
    "5144576": "ES",
    "5145600": "DE",
    "5146084": "CH",
    "5146088": "GB",
    "5146092": "US",
    "5146096": "DE",
    "5146112": "US",
    "5146368": "GB",
    "5146624": "CZ",
    "5147648": "GB",
    "5148672": "CZ",
    "5152768": "DE",
    "5160960": "RU",
    "5165056": "SE",
    "5169152": "BG",
    "5173248": "RU",
    "5177344": "CZ",
    "5178368": "NL",
    "5179392": "DE",
    "5180416": "DK",
    "5180672": "AL",
    "5180928": "SA",
    "5181184": "IE",
    "5181440": "CZ",
    "5185536": "NL",
    "5189632": "GB",
    "5193728": "RU",
    "5197824": "GB",
    "5201920": "NL",
    "5206016": "EE",
    "5210112": "GB",
    "5214208": "LB",
    "5218304": "SE",
    "5222400": "RU",
    "5226496": "NL",
    "5230592": "GB",
    "5234688": "DE",
    "5238784": "RU",
    "5242880": "DK",
    "5243368": "SE",
    "5243372": "DK",
    "5243568": "SE",
    "5243576": "DK",
    "5244136": "SE",
    "5244140": "DK",
    "5244152": "SE",
    "5244160": "DK",
    "5244176": "SE",
    "5244184": "DK",
    "5244792": "SE",
    "5244800": "DK",
    "5244880": "SE",
    "5244888": "DK",
    "5245448": "SE",
    "5245456": "DK",
    "5246304": "SE",
    "5246320": "DK",
    "5246496": "SE",
    "5246504": "DK",
    "5250240": "SE",
    "5250244": "DK",
    "5250600": "BE",
    "5250608": "DK",
    "5250664": "BE",
    "5250672": "DK",
    "5250744": "BE",
    "5250748": "DK",
    "5250752": "BE",
    "5250768": "DK",
    "5250908": "SE",
    "5250912": "DK",
    "5250956": "SE",
    "5250960": "DK",
    "5250972": "SE",
    "5250976": "DK",
    "5251060": "SE",
    "5251064": "DK",
    "5251072": "BA",
    "5255168": "HR",
    "5259264": "SE",
    "5263360": "NL",
    "5263872": "ES",
    "5264384": "AD",
    "5265408": "ES",
    "5265920": "HN",
    "5266432": "AD",
    "5267456": "RU",
    "5275648": "BG",
    "5283840": "XK",
    "5287936": "GB",
    "5292032": "RU",
    "5296128": "UZ",
    "5300224": "CH",
    "5304064": "IT",
    "5304320": "AT",
    "5308416": "DE",
    "5316608": "LV",
    "5318656": "US",
    "5319168": "LV",
    "5320448": "FR",
    "5320704": "LV",
    "5320960": "US",
    "5321472": "LV",
    "5321728": "US",
    "5321984": "LV",
    "5322752": "US",
    "5323008": "LV",
    "5324800": "GB",
    "5325884": "SG",
    "5325888": "GB",
    "5327360": "SG",
    "5327392": "FR",
    "5327424": "GB",
    "5327524": "FR",
    "5327528": "GB",
    "5327532": "SG",
    "5327536": "GB",
    "5332992": "ES",
    "5341184": "SG",
    "5341440": "US",
    "5343232": "NL",
    "5343488": "US",
    "5343744": "DE",
    "5344000": "NL",
    "5344256": "US",
    "5345024": "SG",
    "5345152": "JP",
    "5345280": "LB",
    "5349376": "FI",
    "5357568": "DE",
    "5361664": "RU",
    "5365760": "SK",
    "5369856": "DE",
    "5373952": "IT",
    "5378048": "PL",
    "5382144": "RU",
    "5390336": "NL",
    "5391872": "SC",
    "5392035": "NL",
    "5392036": "SC",
    "5392128": "NL",
    "5394176": "SC",
    "5394259": "NL",
    "5394260": "SC",
    "5394432": "RU",
    "5398528": "DK",
    "5402624": "GB",
    "5410816": "CZ",
    "5414912": "RU",
    "5423104": "CZ",
    "5425152": "DE",
    "5431296": "FR",
    "5435392": "GB",
    "5439488": "FI",
    "5443584": "LB",
    "5447680": "CH",
    "5455872": "CZ",
    "5459968": "NL",
    "5462016": "US",
    "5462528": "SE",
    "5462784": "ES",
    "5463040": "NZ",
    "5464064": "DE",
    "5472256": "GE",
    "5476352": "GB",
    "5480448": "IT",
    "5484544": "DE",
    "5488640": "RU",
    "5492736": "SE",
    "5496832": "RU",
    "5505024": "DE",
    "5509120": "BE",
    "5512448": "HK",
    "5512704": "US",
    "5512960": "BE",
    "5513216": "SE",
    "5517312": "GB",
    "5529600": "IT",
    "5533696": "RU",
    "5537792": "ES",
    "5540096": "BG",
    "5540352": "ES",
    "5540864": "US",
    "5541376": "ES",
    "5542912": "FR",
    "5543168": "ES",
    "5545984": "FR",
    "5546240": "GB",
    "5546496": "SE",
    "5546752": "NL",
    "5547008": "DE",
    "5547264": "FR",
    "5547520": "NL",
    "5547776": "BG",
    "5548032": "GB",
    "5548288": "DE",
    "5548544": "GB",
    "5550080": "UA",
    "5554176": "DE",
    "5562368": "NL",
    "5570560": "DE",
    "5574656": "CY",
    "5578752": "NL",
    "5582848": "HU",
    "5586944": "GB",
    "5591552": "IE",
    "5592064": "GB",
    "5593088": "NL",
    "5595136": "MT",
    "5599232": "SE",
    "5603328": "NL",
    "5607424": "RU",
    "5611520": "NL",
    "5615616": "RU",
    "5619712": "DE",
    "5623808": "GB",
    "5627904": "PL",
    "5632000": "RU",
    "5632256": "FI",
    "5632512": "NL",
    "5634048": "RU",
    "5636096": "DE",
    "5640192": "CA",
    "5644288": "GB",
    "5648384": "IT",
    "5652480": "SE",
    "5656576": "DE",
    "5656832": "FR",
    "5658624": "DE",
    "5659136": "FR",
    "5660672": "RO",
    "5668864": "NO",
    "5672960": "IT",
    "5677056": "DE",
    "5677824": "CH",
    "5677952": "DE",
    "5679360": "AT",
    "5679616": "DE",
    "5685248": "CH",
    "5689344": "NO",
    "5693440": "AM",
    "5697536": "SK",
    "5701632": "GB",
    "5709824": "PL",
    "5713920": "SE",
    "5718016": "GH",
    "5726208": "RU",
    "5730304": "DE",
    "5734400": "GB",
    "5738496": "RU",
    "5742592": "DE",
    "5746688": "CZ",
    "5750784": "RU",
    "5754880": "SK",
    "5758976": "FR",
    "5763072": "BA",
    "5767168": "ZA",
    "5767680": "UG",
    "5767936": "ZM",
    "5768192": "KE",
    "5768960": "NG",
    "5769472": "AO",
    "5769728": "NG",
    "5769984": "ZA",
    "5770240": "DZ",
    "5771264": "DE",
    "5775360": "NL",
    "5779456": "RU",
    "5783552": "DE",
    "5787648": "IT",
    "5791744": "SE",
    "5799936": "DK",
    "5808128": "IT",
    "5812224": "FI",
    "5816320": "GB",
    "5824512": "ES",
    "5826560": "IT",
    "5828608": "BH",
    "5832704": "TW",
    "5832960": "HK",
    "5833216": "VN",
    "5833472": "RU",
    "5833728": "AU",
    "5834752": "RU",
    "5835776": "ES",
    "5836800": "DK",
    "5840896": "NO",
    "5849088": "DE",
    "5851136": "LV",
    "5853184": "GB",
    "5857280": "AT",
    "5861376": "FR",
    "5865472": "RU",
    "5873664": "SE",
    "5877760": "NG",
    "5881088": "LB",
    "5881344": "NG",
    "5881354": "LB",
    "5881355": "NG",
    "5881856": "RU",
    "5885952": "CH",
    "5890048": "NL",
    "5894144": "CY",
    "5898240": "DE",
    "5906432": "LU",
    "5914624": "RU",
    "5918720": "AL",
    "5922816": "DE",
    "5926912": "RU",
    "5931008": "CZ",
    "5935104": "DE",
    "5939200": "JO",
    "5943296": "RU",
    "5944064": "NL",
    "5944320": "RU",
    "5947392": "GB",
    "5951488": "BE",
    "5955584": "UA",
    "5959680": "RU",
    "5963776": "DK",
    "5967872": "RU",
    "5971968": "NO",
    "5976064": "IT",
    "5980160": "ES",
    "5981184": "GB",
    "5981696": "ES",
    "5981952": "TR",
    "5982208": "ES",
    "5982720": "US",
    "5982976": "ES",
    "5983232": "US",
    "5983264": "ES",
    "5983296": "US",
    "5983488": "ES",
    "5983536": "US",
    "5983544": "ES",
    "5983560": "US",
    "5983584": "ES",
    "5983616": "US",
    "5984256": "ES",
    "5984512": "TR",
    "5984768": "ES",
    "5985280": "IL",
    "5985792": "US",
    "5986304": "RO",
    "5986560": "FR",
    "5986816": "ES",
    "5987328": "TR",
    "5988352": "DE",
    "5992448": "AL",
    "5996544": "DK",
    "6000640": "BE",
    "6004736": "UA",
    "6012928": "RU",
    "6017024": "IR",
    "6017280": "KZ",
    "6017536": "MD",
    "6017792": "TH",
    "6018048": "AT",
    "6018304": "CY",
    "6018560": "UA",
    "6018816": "FR",
    "6019072": "TR",
    "6019328": "DE",
    "6019584": "RU",
    "6019840": "NL",
    "6020096": "CZ",
    "6020352": "US",
    "6020608": "GB",
    "6020864": "DE",
    "6021120": "SE",
    "6027520": "",
    "6027776": "SE",
    "6027978": "DE",
    "6027979": "SE",
    "6028890": "US",
    "6028891": "SE",
    "6029312": "RU",
    "6041600": "DE",
    "6044416": "FJ",
    "6044672": "DE",
    "6045696": "LU",
    "6053888": "RU",
    "6057984": "AT",
    "6062080": "SE",
    "6066176": "GB",
    "6070272": "RU",
    "6074368": "GE",
    "6078464": "KZ",
    "6080256": "RU",
    "6080512": "NL",
    "6081536": "RU",
    "6081919": "US",
    "6081920": "RU",
    "6086656": "UA",
    "6090752": "CZ",
    "6094848": "IE",
    "6094849": "US",
    "6094851": "IE",
    "6094884": "US",
    "6094886": "IE",
    "6095256": "US",
    "6095260": "IE",
    "6096512": "US",
    "6096640": "IE",
    "6096903": "US",
    "6096904": "IE",
    "6096905": "US",
    "6096906": "IE",
    "6097244": "US",
    "6097248": "IE",
    "6097256": "CH",
    "6097260": "US",
    "6097264": "IE",
    "6097296": "US",
    "6097300": "IE",
    "6097544": "US",
    "6097552": "IE",
    "6103040": "AT",
    "6107136": "RU",
    "6111232": "IT",
    "6115328": "FR",
    "6119424": "RU",
    "6123520": "UA",
    "6127616": "IT",
    "6131712": "MT",
    "6135808": "GB",
    "6139904": "RU",
    "6144000": "GB",
    "6145280": "SG",
    "6145536": "GB",
    "6146304": "HK",
    "6146560": "US",
    "6146816": "GB",
    "6148096": "TR",
    "6148352": "BR",
    "6148608": "GR",
    "6148864": "LU",
    "6149120": "TR",
    "6149632": "NL",
    "6149888": "CO",
    "6150144": "TR",
    "6150400": "FR",
    "6150656": "NL",
    "6150912": "US",
    "6151168": "TR",
    "6151424": "US",
    "6151680": "KR",
    "6151936": "LU",
    "6152192": "RS",
    "6160384": "ES",
    "6164480": "PL",
    "6168576": "GB",
    "6172672": "SK",
    "6176768": "NL",
    "6177988": "IE",
    "6177990": "NL",
    "6180864": "IR",
    "6181376": "DE",
    "6181888": "RU",
    "6182912": "PL",
    "6183168": "SG",
    "6183424": "BR",
    "6183680": "IN",
    "6183936": "RO",
    "6184086": "GB",
    "6184087": "RO",
    "6184960": "MC",
    "6189056": "IT",
    "6193152": "DE",
    "6197248": "CH",
    "6201344": "BY",
    "6205440": "FR",
    "6209536": "GB",
    "6213632": "SE",
    "6217728": "BY",
    "6221824": "MD",
    "6225920": "ZA",
    "6230016": "BG",
    "6234112": "RU",
    "6238208": "GB",
    "6242304": "HU",
    "6250496": "CZ",
    "6258688": "FI",
    "6262784": "DE",
    "6266880": "NL",
    "6270976": "GB",
    "6279168": "BH",
    "6283264": "SI",
    "6287360": "CZ",
    "6291456": "RO",
    "6301184": "BR",
    "6301440": "BE",
    "6301696": "RO",
    "6302720": "PL",
    "6302976": "IT",
    "6303232": "RO",
    "6314240": "BR",
    "6314496": "IT",
    "6315008": "RO",
    "6331392": "JP",
    "6331648": "US",
    "6332160": "ES",
    "6332416": "RO",
    "6351872": "IT",
    "6352384": "RO",
    "6367232": "BE",
    "6367488": "CH",
    "6367744": "CA",
    "6368000": "RO",
    "6368256": "AU",
    "6368512": "DE",
    "6368768": "HK",
    "6369024": "US",
    "6369280": "RO",
    "6370816": "FR",
    "6371072": "RO",
    "6381568": "BG",
    "6381824": "RO",
    "6397952": "MD",
    "6398464": "RO",
    "6422528": "HU",
    "6553600": "NL",
    "6684672": "ES",
    "6815744": "IT",
    "6946816": "GR",
    "7077888": "AT",
    "7274496": "IE",
    "7340032": "NL",
    "7585792": "RU",
    "7593984": "NL",
    "7602176": "IT",
    "7733248": "FR",
    "7864320": "AT",
    "7907094": "SI",
    "7907095": "AT",
    "8041799": "FR",
    "8041800": "AT",
    "8126464": "FR",
    "8257536": "SE",
    "8257792": "US",
    "8388608": "DE",
    "8585804": "JP",
    "8585805": "DE",
    "9808396": "GR",
    "9808400": "DE",
    "9854339": "",
    "9854340": "DE",
    "10073668": "CH",
    "10073669": "DE",
    "10234880": "FR",
    "10235136": "DE",
    "10291200": "US",
    "10291712": "DE",
    "10291737": "US",
    "10291738": "CA",
    "10291739": "DE",
    "10291784": "US",
    "10291792": "CA",
    "10291800": "DE",
    "10291840": "US",
    "10292480": "DE",
    "10292736": "US",
    "10293248": "DE",
    "10485760": "DK",
    "11010048": "GB",
    "11079832": "ES",
    "11079840": "GB",
    "11080704": "SE",
    "11080712": "GB",
    "11080716": "SE",
    "11080720": "GB",
    "11080724": "DE",
    "11080728": "SE",
    "11080732": "GB",
    "11080736": "DK",
    "11080740": "SE",
    "11080748": "GB",
    "11080752": "SE",
    "11080756": "GB",
    "11080764": "SE",
    "11080778": "GB",
    "11080780": "SE",
    "11080804": "GB",
    "11080808": "SE",
    "11080848": "GB",
    "11080862": "SE",
    "11080868": "GB",
    "11080872": "SE",
    "11080876": "GB",
    "11080880": "SE",
    "11080888": "GB",
    "11080892": "SE",
    "11080900": "DK",
    "11080904": "SE",
    "11080912": "GB",
    "11080916": "DK",
    "11080920": "SE",
    "11080924": "GB",
    "11080928": "SE",
    "11080940": "GB",
    "11080944": "SE",
    "11080960": "GB",
    "11080976": "SE",
    "11080980": "GB",
    "11080984": "SE",
    "11080988": "GB",
    "11080996": "SE",
    "11081000": "GB",
    "11081008": "SE",
    "11081012": "GB",
    "11081016": "SE",
    "11081024": "GB",
    "11081032": "SE",
    "11081038": "GB",
    "11081056": "SE",
    "11081060": "GB",
    "11081076": "SE",
    "11081084": "GB",
    "11081116": "SE",
    "11081120": "GB",
    "11081130": "SE",
    "11081136": "GB",
    "11081140": "SE",
    "11081144": "GB",
    "11081152": "SE",
    "11081160": "GB",
    "11081176": "SE",
    "11081180": "GB",
    "11081200": "SE",
    "11081208": "GB",
    "11081212": "SE",
    "11081248": "DE",
    "11081280": "SE",
    "11081400": "DE",
    "11081408": "SE",
    "11081520": "AT",
    "11081528": "SE",
    "11081592": "NO",
    "11081600": "SE",
    "11081728": "GB",
    "11083848": "ES",
    "11083852": "GB",
    "11084320": "NL",
    "11084328": "GB",
    "11089896": "AT",
    "11089904": "GB",
    "11090176": "IE",
    "11090944": "GB",
    "11090984": "NL",
    "11090992": "GB",
    "11091168": "IT",
    "11091184": "GB",
    "11091200": "BE",
    "11091400": "LU",
    "11091408": "BE",
    "11091456": "GB",
    "11091468": "BE",
    "11091480": "GB",
    "11091484": "BE",
    "11091488": "GB",
    "11091522": "BE",
    "11091524": "GB",
    "11091536": "BE",
    "11091544": "GB",
    "11091548": "BE",
    "11091560": "GB",
    "11091564": "BE",
    "11091570": "LU",
    "11091572": "GB",
    "11091576": "BE",
    "11091580": "GB",
    "11091584": "NL",
    "11091588": "BE",
    "11091596": "GB",
    "11091608": "LU",
    "11091610": "BE",
    "11091624": "GB",
    "11091636": "BE",
    "11091640": "GB",
    "11091646": "BE",
    "11091648": "GB",
    "11091652": "BE",
    "11091680": "LU",
    "11091684": "BE",
    "11091686": "GB",
    "11091688": "LU",
    "11091690": "GB",
    "11091692": "BE",
    "11091704": "GB",
    "11091708": "BE",
    "11091784": "NL",
    "11091792": "BE",
    "11091968": "GB",
    "11092228": "AT",
    "11092248": "GB",
    "11092288": "AT",
    "11092472": "GB",
    "11093248": "IT",
    "11093504": "DE",
    "11093512": "IT",
    "11094016": "GB",
    "11094028": "AT",
    "11094032": "GB",
    "11094040": "AT",
    "11094064": "GB",
    "11094066": "AT",
    "11094068": "GB",
    "11094072": "AT",
    "11094088": "GB",
    "11094092": "AT",
    "11094096": "GB",
    "11094100": "AT",
    "11094104": "GB",
    "11094106": "AT",
    "11094112": "GB",
    "11094116": "AT",
    "11094136": "GB",
    "11094140": "AT",
    "11094160": "GB",
    "11094164": "AT",
    "11094168": "GB",
    "11094184": "AT",
    "11094188": "GB",
    "11094196": "AT",
    "11094228": "GB",
    "11094236": "AT",
    "11094528": "ES",
    "11095048": "GB",
    "11095052": "ES",
    "11095056": "GB",
    "11095064": "ES",
    "11095080": "GB",
    "11095084": "ES",
    "11095088": "GB",
    "11095096": "ES",
    "11095106": "GB",
    "11095108": "ES",
    "11095114": "GB",
    "11095116": "ES",
    "11095120": "GB",
    "11095124": "ES",
    "11095128": "GB",
    "11095140": "ES",
    "11095154": "GB",
    "11095160": "ES",
    "11095164": "GB",
    "11095168": "ES",
    "11095172": "GB",
    "11095176": "ES",
    "11095188": "GB",
    "11095192": "ES",
    "11095196": "GB",
    "11095200": "ES",
    "11095216": "GB",
    "11095228": "ES",
    "11095252": "GB",
    "11095256": "ES",
    "11095280": "GB",
    "11095284": "ES",
    "11095290": "GB",
    "11095292": "ES",
    "11096064": "BE",
    "11096584": "GB",
    "11096588": "BE",
    "11096608": "GB",
    "11096616": "BE",
    "11096624": "GB",
    "11096628": "LU",
    "11096630": "BE",
    "11096632": "LU",
    "11096636": "BE",
    "11096644": "GB",
    "11096648": "BE",
    "11096652": "NL",
    "11096656": "BE",
    "11096696": "GB",
    "11096700": "BE",
    "11096704": "GB",
    "11096708": "BE",
    "11096712": "GB",
    "11096716": "BE",
    "11096724": "GB",
    "11096728": "BE",
    "11096732": "GB",
    "11096736": "BE",
    "11096744": "GB",
    "11096748": "BE",
    "11096768": "GB",
    "11096772": "BE",
    "11096776": "GB",
    "11096780": "BE",
    "11096782": "GB",
    "11096796": "BE",
    "11096804": "GB",
    "11096816": "BE",
    "11096824": "LU",
    "11096826": "BE",
    "11096976": "LU",
    "11096984": "BE",
    "11097088": "ES",
    "11097120": "GB",
    "11097128": "ES",
    "11097132": "GB",
    "11097136": "ES",
    "11097140": "GB",
    "11097152": "ES",
    "11097154": "GB",
    "11097164": "ES",
    "11097176": "GB",
    "11097184": "ES",
    "11097188": "GB",
    "11097196": "ES",
    "11097216": "GB",
    "11097220": "ES",
    "11097224": "GB",
    "11097234": "ES",
    "11097240": "GB",
    "11097244": "ES",
    "11097248": "GB",
    "11097252": "ES",
    "11097256": "GB",
    "11097260": "ES",
    "11097264": "GB",
    "11097268": "ES",
    "11097272": "GB",
    "11097280": "ES",
    "11097288": "GB",
    "11097292": "ES",
    "11097296": "GB",
    "11097300": "ES",
    "11097312": "GB",
    "11097316": "ES",
    "11097320": "GB",
    "11097322": "ES",
    "11097332": "GB",
    "11097336": "ES",
    "11098112": "GB",
    "11098364": "DE",
    "11098368": "GB",
    "11099728": "ES",
    "11099732": "GB",
    "11100288": "ES",
    "11100304": "GB",
    "11100672": "IE",
    "11100824": "GB",
    "11100832": "IE",
    "11100928": "GB",
    "11101440": "AT",
    "11101688": "DE",
    "11101696": "GB",
    "11102096": "DE",
    "11102104": "GB",
    "11102208": "IT",
    "11102240": "DE",
    "11102248": "IT",
    "11103744": "BE",
    "11103752": "GB",
    "11103764": "BE",
    "11103772": "GB",
    "11103776": "BE",
    "11103784": "GB",
    "11103792": "BE",
    "11103798": "GB",
    "11103802": "BE",
    "11103824": "GB",
    "11103832": "BE",
    "11103836": "GB",
    "11103852": "BE",
    "11103856": "GB",
    "11103864": "BE",
    "11103866": "GB",
    "11103868": "BE",
    "11103872": "GB",
    "11103876": "BE",
    "11103878": "GB",
    "11103888": "BE",
    "11103900": "GB",
    "11103904": "BE",
    "11103908": "GB",
    "11103916": "BE",
    "11103924": "GB",
    "11103928": "BE",
    "11103932": "GB",
    "11103940": "BE",
    "11103944": "GB",
    "11103948": "BE",
    "11103952": "GB",
    "11103964": "BE",
    "11103984": "GB",
    "11103988": "BE",
    "11104256": "GB",
    "11104768": "IT",
    "11105036": "GB",
    "11105040": "IT",
    "11105052": "GB",
    "11105056": "IT",
    "11105060": "GB",
    "11105076": "IT",
    "11105136": "GB",
    "11105144": "IT",
    "11105156": "GB",
    "11105160": "IT",
    "11105164": "GB",
    "11105168": "IT",
    "11105172": "GB",
    "11105176": "IT",
    "11105188": "GB",
    "11105192": "IT",
    "11105196": "GB",
    "11105200": "IT",
    "11105220": "GB",
    "11105232": "IT",
    "11105236": "GB",
    "11105240": "IT",
    "11105268": "GB",
    "11105616": "DE",
    "11105632": "ES",
    "11105636": "DE",
    "11105640": "GB",
    "11105792": "IT",
    "11105804": "GB",
    "11105806": "IT",
    "11105812": "GB",
    "11105820": "IT",
    "11105824": "GB",
    "11105828": "IT",
    "11105846": "GB",
    "11105856": "IT",
    "11105860": "GB",
    "11105866": "IT",
    "11105872": "GB",
    "11105884": "IT",
    "11105912": "GB",
    "11105916": "IT",
    "11105920": "GB",
    "11105932": "IT",
    "11105940": "GB",
    "11105948": "IT",
    "11105950": "GB",
    "11105956": "IT",
    "11105960": "GB",
    "11105962": "IT",
    "11105968": "GB",
    "11105980": "IT",
    "11105984": "GB",
    "11105990": "IT",
    "11106008": "GB",
    "11106020": "IT",
    "11106036": "GB",
    "11107612": "ES",
    "11107616": "GB",
    "11107704": "ES",
    "11107712": "GB",
    "11108672": "NL",
    "11108688": "GB",
    "11109760": "DE",
    "11109776": "GB",
    "11110048": "IE",
    "11110080": "GB",
    "11110400": "IE",
    "11110410": "GB",
    "11110412": "IE",
    "11110416": "GB",
    "11110424": "IE",
    "11110432": "GB",
    "11110434": "IE",
    "11110436": "GB",
    "11110440": "IE",
    "11110456": "GB",
    "11110460": "IE",
    "11110480": "GB",
    "11110492": "IE",
    "11110504": "GB",
    "11110508": "IE",
    "11110512": "GB",
    "11110528": "IE",
    "11110532": "GB",
    "11110536": "IE",
    "11110540": "GB",
    "11110544": "IE",
    "11110556": "GB",
    "11110560": "IE",
    "11110568": "GB",
    "11110572": "IE",
    "11110580": "GB",
    "11110584": "IE",
    "11110588": "GB",
    "11110592": "IE",
    "11110612": "GB",
    "11110616": "IE",
    "11110636": "GB",
    "11110640": "IE",
    "11110644": "GB",
    "11110648": "IE",
    "11110652": "GB",
    "11110656": "IE",
    "11110744": "DE",
    "11110752": "IE",
    "11111392": "GB",
    "11111400": "IE",
    "11112384": "GB",
    "11113024": "DE",
    "11113032": "FR",
    "11113040": "GB",
    "11113296": "FR",
    "11113304": "GB",
    "11118160": "DE",
    "11118168": "GB",
    "11121408": "SE",
    "11121920": "DK",
    "11121928": "SE",
    "11121976": "NO",
    "11121984": "SE",
    "11122264": "DK",
    "11122272": "SE",
    "11122416": "DK",
    "11122432": "SE",
    "11123208": "GB",
    "11123216": "SE",
    "11123220": "DE",
    "11123224": "GB",
    "11123252": "DE",
    "11123256": "SE",
    "11123280": "GB",
    "11123284": "SE",
    "11123288": "GB",
    "11123304": "SE",
    "11123312": "GB",
    "11123320": "DE",
    "11123324": "SE",
    "11123332": "GB",
    "11123344": "SE",
    "11123380": "GB",
    "11123392": "DE",
    "11123396": "SE",
    "11123400": "DE",
    "11123408": "GB",
    "11123412": "DE",
    "11123416": "DK",
    "11123420": "GB",
    "11123428": "SE",
    "11123440": "DE",
    "11123444": "SE",
    "11123456": "IT",
    "11123712": "GB",
    "11125348": "IE",
    "11125352": "GB",
    "11125368": "DE",
    "11125372": "GB",
    "11126496": "FR",
    "11126500": "GB",
    "11128832": "ES",
    "11129152": "GB",
    "11129160": "ES",
    "11129184": "GB",
    "11129240": "ES",
    "11129256": "GB",
    "11129260": "ES",
    "11129272": "GB",
    "11129312": "ES",
    "11129320": "GB",
    "11129344": "IE",
    "11129600": "BE",
    "11129612": "GB",
    "11129616": "LU",
    "11129618": "BE",
    "11129624": "GB",
    "11129628": "BE",
    "11129632": "GB",
    "11129640": "BE",
    "11129648": "GB",
    "11129652": "BE",
    "11129656": "NL",
    "11129660": "GB",
    "11129664": "BE",
    "11129696": "GB",
    "11129700": "BE",
    "11129704": "GB",
    "11129712": "BE",
    "11129722": "GB",
    "11129730": "BE",
    "11129736": "NL",
    "11129740": "GB",
    "11129744": "BE",
    "11129752": "GB",
    "11129756": "BE",
    "11129760": "GB",
    "11129762": "BE",
    "11129764": "GB",
    "11129768": "BE",
    "11129772": "GB",
    "11129776": "BE",
    "11129784": "GB",
    "11129788": "BE",
    "11129812": "GB",
    "11129816": "BE",
    "11129844": "GB",
    "11129852": "BE",
    "11129856": "GB",
    "11130912": "IE",
    "11130920": "GB",
    "11130928": "IE",
    "11130968": "GB",
    "11130976": "IE",
    "11130992": "GB",
    "11131032": "IE",
    "11131040": "GB",
    "11131048": "IE",
    "11131156": "GB",
    "11131168": "IE",
    "11131180": "GB",
    "11131184": "IE",
    "11131204": "GB",
    "11131212": "IE",
    "11131220": "GB",
    "11131228": "IE",
    "11131240": "GB",
    "11131244": "IE",
    "11131260": "GB",
    "11131264": "IE",
    "11131268": "GB",
    "11131272": "IE",
    "11131276": "GB",
    "11131284": "IE",
    "11131296": "GB",
    "11131300": "IE",
    "11131308": "GB",
    "11131312": "IE",
    "11131316": "GB",
    "11131328": "IE",
    "11131356": "GB",
    "11131360": "IE",
    "11131392": "GB",
    "11131404": "ES",
    "11131408": "GB",
    "11131656": "IE",
    "11131680": "GB",
    "11131688": "IE",
    "11131712": "GB",
    "11131720": "IE",
    "11131728": "GB",
    "11131736": "IE",
    "11131744": "GB",
    "11131752": "IE",
    "11131760": "GB",
    "11131768": "IE",
    "11131784": "GB",
    "11131792": "IE",
    "11131824": "GB",
    "11131856": "IE",
    "11131864": "GB",
    "11131872": "IE",
    "11131888": "GB",
    "11133184": "ES",
    "11133440": "IT",
    "11133444": "GB",
    "11133448": "IT",
    "11133456": "GB",
    "11133460": "IT",
    "11133468": "GB",
    "11133472": "IT",
    "11133480": "GB",
    "11133484": "IT",
    "11133486": "GB",
    "11133490": "IT",
    "11133492": "GB",
    "11133504": "IT",
    "11133512": "GB",
    "11133514": "IT",
    "11133516": "GB",
    "11133520": "IT",
    "11133524": "GB",
    "11133526": "IT",
    "11133528": "GB",
    "11133532": "IT",
    "11133536": "GB",
    "11133540": "IT",
    "11133552": "GB",
    "11133556": "IT",
    "11133560": "GB",
    "11133564": "IT",
    "11133572": "GB",
    "11133576": "IT",
    "11133584": "GB",
    "11133586": "IT",
    "11133592": "GB",
    "11133600": "IT",
    "11133604": "GB",
    "11133612": "IT",
    "11133620": "GB",
    "11133632": "IT",
    "11133636": "GB",
    "11133648": "IT",
    "11133660": "GB",
    "11133668": "IT",
    "11133672": "GB",
    "11133676": "IT",
    "11133692": "GB",
    "11133696": "IT",
    "11133952": "GB",
    "11133956": "IE",
    "11133968": "GB",
    "11133976": "IE",
    "11133992": "GB",
    "11133996": "IE",
    "11134000": "GB",
    "11134008": "IE",
    "11134040": "GB",
    "11134048": "IE",
    "11134096": "GB",
    "11134112": "IE",
    "11134116": "GB",
    "11134124": "IE",
    "11134140": "GB",
    "11134148": "IE",
    "11134164": "GB",
    "11134168": "IE",
    "11134188": "GB",
    "11134192": "IE",
    "11134248": "GB",
    "11134280": "IE",
    "11134296": "GB",
    "11134304": "IE",
    "11134328": "GB",
    "11134360": "IE",
    "11134400": "GB",
    "11134424": "IE",
    "11134440": "GB",
    "11134456": "IE",
    "11134464": "GB",
    "11134976": "CH",
    "11135488": "IT",
    "11136000": "IE",
    "11136264": "GB",
    "11136268": "IE",
    "11136272": "GB",
    "11136276": "IE",
    "11136280": "GB",
    "11136284": "IE",
    "11136292": "GB",
    "11136296": "IE",
    "11136304": "GB",
    "11136308": "IE",
    "11136312": "GB",
    "11136316": "IE",
    "11136328": "GB",
    "11136332": "IE",
    "11136350": "GB",
    "11136352": "IE",
    "11136372": "GB",
    "11136376": "IE",
    "11136428": "GB",
    "11136432": "IE",
    "11136448": "GB",
    "11136452": "IE",
    "11136462": "GB",
    "11136464": "IE",
    "11136472": "GB",
    "11136480": "IE",
    "11136496": "GB",
    "11136504": "IE",
    "11136512": "GB",
    "11137024": "CH",
    "11137536": "GB",
    "11138048": "ES",
    "11138208": "DE",
    "11138216": "ES",
    "11138816": "GB",
    "11138820": "ES",
    "11138828": "GB",
    "11138840": "ES",
    "11138844": "GB",
    "11138848": "ES",
    "11138854": "GB",
    "11138860": "ES",
    "11138864": "GB",
    "11138868": "ES",
    "11138872": "GB",
    "11138876": "ES",
    "11138884": "GB",
    "11138888": "ES",
    "11138916": "GB",
    "11138920": "ES",
    "11138936": "GB",
    "11138940": "ES",
    "11138944": "GB",
    "11138948": "ES",
    "11138952": "GB",
    "11138964": "ES",
    "11138972": "GB",
    "11138980": "ES",
    "11138988": "GB",
    "11138992": "ES",
    "11139008": "GB",
    "11139016": "ES",
    "11139024": "GB",
    "11139028": "ES",
    "11139032": "GB",
    "11139036": "ES",
    "11139052": "GB",
    "11139056": "ES",
    "11139064": "GB",
    "11139070": "ES",
    "11139072": "GB",
    "11141120": "SE",
    "11206656": "DE",
    "11272192": "PT",
    "11337728": "ES",
    "11386880": "US",
    "11388928": "CZ",
    "11389952": "TR",
    "11390976": "DE",
    "11395072": "IT",
    "11396096": "IQ",
    "11396608": "NO",
    "11397120": "US",
    "11403264": "ES",
    "11432704": "GB",
    "11432960": "ES",
    "11438548": "CH",
    "11438549": "ES",
    "11460608": "US",
    "11464704": "ES",
    "11466752": "DE",
    "11467008": "JP",
    "11467264": "PL",
    "11467520": "CA",
    "11467776": "ES",
    "11468544": "DE",
    "11468800": "GB",
    "11665408": "IL",
    "11796480": "IT",
    "12058624": "KW",
    "12124160": "FR",
    "12189696": "FI",
    "12255232": "DE",
    "12293888": "",
    "12294400": "DE",
    "12294656": "",
    "12294912": "DE",
    "12295680": "",
    "12295936": "DE",
    "12308480": "",
    "12310016": "DE",
    "12311296": "",
    "12311552": "DE",
    "12311808": "",
    "12312576": "DE",
    "12320768": "CZ",
    "12386304": "GB",
    "12451840": "IE",
    "12452864": "DE",
    "12472320": "GB",
    "12474368": "DE",
    "12517376": "IR",
    "12582912": "GB",
    "12845056": "DK",
    "12906276": "US",
    "12906280": "DK",
    "13107200": "BE",
    "13238272": "NO",
    "13336576": "US",
    "13369344": "IT",
    "13631488": "DK",
    "13664256": "CH",
    "13680640": "JP",
    "13684736": "DE",
    "13686784": "GB",
    "13688832": "LT",
    "13690880": "DE",
    "13692928": "FI",
    "13694976": "IT",
    "13696000": "US",
    "13696256": "GB",
    "13696512": "RO",
    "13696768": "DE",
    "13697024": "DK",
    "13729792": "GB",
    "13746176": "DE",
    "13754368": "LT",
    "13758464": "US",
    "13759488": "DE",
    "13760512": "PL",
    "13761536": "NL",
    "13762048": "RO",
    "13762304": "ES",
    "13762560": "IR",
    "13778944": "DK",
    "13787136": "IT",
    "13795328": "IR",
    "13828096": "IT",
    "13877248": "CZ",
    "13885440": "IT",
    "13889536": "PL",
    "13893632": "NO",
    "14024704": "FR",
    "14155776": "SE",
    "14286848": "CH",
    "14417920": "FI",
    "14680064": "ES",
    "14745600": "SA",
    "14747264": "SE",
    "14747648": "SA",
    "14751744": "SE",
    "14753792": "AE",
    "14755456": "SE",
    "14755840": "AE",
    "14759936": "SE",
    "14761984": "SA",
    "14766080": "IT",
    "14770176": "AE",
    "14771840": "SE",
    "14772224": "AE",
    "14776320": "SE",
    "14778368": "MA",
    "14781440": "SE",
    "14781952": "MA",
    "14783488": "SE",
    "14784512": "MA",
    "14786560": "ES",
    "14791680": "SE",
    "14792704": "ES",
    "14794752": "IN",
    "14811136": "DE",
    "14876672": "AE",
    "14942208": "DE",
    "15007744": "GB",
    "15073280": "IL",
    "15138816": "ES",
    "15139328": "GB",
    "15140160": "CA",
    "15140272": "GB",
    "15140352": "TR",
    "15140626": "DE",
    "15140628": "TR",
    "15140630": "DE",
    "15140632": "TR",
    "15140652": "CA",
    "15140864": "FR",
    "15140880": "CA",
    "15140912": "FR",
    "15140939": "CA",
    "15140940": "FR",
    "15140976": "CA",
    "15140977": "FR",
    "15140978": "CA",
    "15140980": "FR",
    "15141043": "CA",
    "15141044": "FR",
    "15141906": "GB",
    "15141907": "FR",
    "15142223": "CA",
    "15142224": "FR",
    "15142376": "ES",
    "15142380": "FR",
    "15142422": "ES",
    "15142424": "FR",
    "15142912": "CA",
    "15143424": "DK",
    "15143552": "CA",
    "15143712": "GB",
    "15143720": "CA",
    "15143744": "GB",
    "15144064": "CA",
    "15144192": "PT",
    "15144205": "CA",
    "15144206": "PT",
    "15144214": "CA",
    "15144216": "PT",
    "15144220": "CA",
    "15144448": "GB",
    "15144960": "DE",
    "15144976": "CA",
    "15145472": "DE",
    "15145692": "GB",
    "15145696": "DE",
    "15145984": "CA",
    "15146496": "SE",
    "15146571": "CA",
    "15146573": "SE",
    "15146644": "CA",
    "15146648": "SE",
    "15146656": "CA",
    "15147008": "GB",
    "15147040": "PL",
    "15147052": "GB",
    "15147054": "PL",
    "15147055": "GB",
    "15147060": "PL",
    "15147068": "GB",
    "15147069": "PL",
    "15147070": "GB",
    "15147072": "PL",
    "15147084": "GB",
    "15147088": "PL",
    "15147096": "GB",
    "15147136": "PL",
    "15147200": "GB",
    "15150080": "FR",
    "15150448": "GB",
    "15150464": "FR",
    "15150720": "GB",
    "15151872": "NL",
    "15151884": "GB",
    "15151888": "NL",
    "15151904": "GB",
    "15151920": "NL",
    "15151936": "GB",
    "15152128": "BE",
    "15152136": "GB",
    "15152137": "NL",
    "15152138": "GB",
    "15154432": "ES",
    "15154688": "GB",
    "15154944": "FR",
    "15155200": "DE",
    "15155584": "GB",
    "15156224": "FR",
    "15156480": "GB",
    "15156992": "AT",
    "15157120": "FR",
    "15157192": "GB",
    "15157200": "FR",
    "15157237": "GB",
    "15157238": "FR",
    "15157248": "GB",
    "15158528": "PL",
    "15158540": "IT",
    "15158544": "PL",
    "15158552": "IT",
    "15158784": "GB",
    "15159296": "NL",
    "15159424": "GB",
    "15160356": "NL",
    "15160360": "GB",
    "15160832": "ES",
    "15160833": "GB",
    "15160836": "ES",
    "15160872": "GB",
    "15161600": "NO",
    "15161856": "GB",
    "15162112": "ES",
    "15162240": "GB",
    "15162880": "DE",
    "15163136": "GB",
    "15165440": "ES",
    "15165460": "GB",
    "15166240": "FR",
    "15166256": "GB",
    "15166720": "DK",
    "15166730": "GB",
    "15166732": "DK",
    "15166736": "GB",
    "15166740": "DK",
    "15166744": "GB",
    "15166976": "FR",
    "15167002": "GB",
    "15167008": "FR",
    "15167069": "GB",
    "15167232": "FR",
    "15167488": "GB",
    "15169536": "FR",
    "15169556": "GB",
    "15169568": "FR",
    "15169584": "GB",
    "15169792": "ES",
    "15170048": "FR",
    "15170096": "GB",
    "15170176": "FR",
    "15170560": "PL",
    "15170816": "DE",
    "15170944": "GB",
    "15171080": "ES",
    "15171088": "GB",
    "15171136": "ES",
    "15171328": "FR",
    "15171340": "GB",
    "15171584": "DE",
    "15171840": "GB",
    "15173888": "ES",
    "15173890": "PL",
    "15173892": "ES",
    "15173934": "GB",
    "15177984": "FR",
    "15178496": "GB",
    "15179008": "ES",
    "15179264": "PT",
    "15179776": "GB",
    "15182336": "ES",
    "15182720": "GB",
    "15183066": "LU",
    "15183067": "GB",
    "15183104": "FR",
    "15183140": "GB",
    "15183360": "DE",
    "15183616": "GB",
    "15186176": "DE",
    "15186320": "GB",
    "15186432": "DE",
    "15186448": "GB",
    "15186688": "DE",
    "15186944": "GB",
    "15188992": "FR",
    "15189248": "GB",
    "15189680": "BE",
    "15189688": "GB",
    "15190016": "FR",
    "15190272": "GB",
    "15190784": "NL",
    "15190816": "TR",
    "15190824": "GB",
    "15191040": "NL",
    "15191056": "GB",
    "15191072": "NL",
    "15191104": "GB",
    "15191168": "NL",
    "15191200": "GB",
    "15191296": "NL",
    "15191424": "GB",
    "15192064": "RO",
    "15192341": "GB",
    "15192344": "RO",
    "15192356": "HU",
    "15192360": "RO",
    "15192372": "GB",
    "15192832": "TR",
    "15192840": "GB",
    "15193088": "SA",
    "15193120": "GB",
    "15193344": "SA",
    "15193600": "GB",
    "15193736": "CZ",
    "15193740": "GB",
    "15193856": "CZ",
    "15193870": "GB",
    "15194368": "FR",
    "15194624": "GB",
    "15195648": "TR",
    "15195650": "GB",
    "15195652": "TR",
    "15195656": "GB",
    "15199330": "BE",
    "15199332": "GB",
    "15199333": "BE",
    "15199334": "GB",
    "15199349": "IT",
    "15199350": "IE",
    "15199351": "GB",
    "15200256": "FR",
    "15201410": "GB",
    "15201411": "FR",
    "15201522": "GB",
    "15201536": "FR",
    "15201600": "GB",
    "15201792": "FR",
    "15202560": "GB",
    "15204352": "NO",
    "15237120": "LV",
    "15269888": "IE",
    "15302656": "LV",
    "15335424": "RU",
    "15368192": "GB",
    "15400960": "EE",
    "15433728": "GB",
    "15466496": "FR",
    "15499264": "BE",
    "15532032": "RU",
    "15564800": "DE",
    "15572992": "FR",
    "15577088": "DE",
    "15597473": "CH",
    "15597475": "DE",
    "15597568": "GB",
    "15613952": "PL",
    "15630336": "SA",
    "15631360": "SG",
    "15632384": "SA",
    "15633408": "HK",
    "15634432": "SG",
    "15635456": "ZA",
    "15636480": "SA",
    "15637504": "CL",
    "15638528": "SG",
    "15639552": "TR",
    "15640576": "MX",
    "15641600": "HK",
    "15643648": "NG",
    "15643904": "CO",
    "15644160": "SG",
    "15644416": "TH",
    "15644928": "PH",
    "15645184": "AE",
    "15645440": "CO",
    "15645696": "NG",
    "15645952": "SG",
    "15646208": "HK",
    "15646464": "SG",
    "15646720": "SA",
    "15659008": "ZA",
    "15663104": "NO",
    "15695872": "FR",
    "15697952": "GB",
    "15697968": "FR",
    "15697976": "GB",
    "15697984": "DK",
    "15698000": "FR",
    "15698016": "SE",
    "15698048": "DE",
    "15698080": "FR",
    "15698112": "PL",
    "15698120": "GB",
    "15698128": "FR",
    "15698688": "DE",
    "15698816": "GB",
    "15698824": "DE",
    "15698832": "SE",
    "15698848": "GB",
    "15698864": "ES",
    "15698872": "FR",
    "15698928": "ES",
    "15698932": "FR",
    "15698936": "IT",
    "15698944": "BG",
    "15698960": "DK",
    "15698968": "DE",
    "15698976": "FR",
    "15699008": "DE",
    "15699040": "SE",
    "15699056": "FR",
    "15699088": "RS",
    "15699104": "FR",
    "15699120": "CZ",
    "15699128": "FR",
    "15699136": "NL",
    "15699168": "GB",
    "15699176": "FR",
    "15699200": "DE",
    "15699204": "IL",
    "15699208": "FR",
    "15699212": "IE",
    "15699216": "BG",
    "15699232": "FR",
    "15699328": "DE",
    "15699584": "FR",
    "15699728": "NL",
    "15699736": "DE",
    "15699740": "ES",
    "15699744": "US",
    "15699760": "FR",
    "15699768": "ES",
    "15699776": "DE",
    "15699784": "ES",
    "15699792": "FR",
    "15699796": "BE",
    "15699800": "FR",
    "15699808": "DE",
    "15699824": "FR",
    "15699832": "GB",
    "15699840": "NL",
    "15699952": "DE",
    "15700032": "FR",
    "15700048": "DE",
    "15700064": "FR",
    "15700096": "GB",
    "15700160": "FR",
    "15700992": "FI",
    "15701024": "FR",
    "15701056": "PL",
    "15701064": "NO",
    "15701072": "DE",
    "15701080": "IT",
    "15701084": "PL",
    "15701088": "DE",
    "15701092": "IT",
    "15701096": "LT",
    "15701104": "DE",
    "15701120": "FR",
    "15701248": "ES",
    "15701256": "IE",
    "15701264": "DE",
    "15701280": "GB",
    "15701288": "BE",
    "15701296": "GB",
    "15701304": "DE",
    "15701312": "FR",
    "15701371": "PL",
    "15701375": "FR",
    "15701440": "PL",
    "15701456": "IT",
    "15701464": "FR",
    "15701472": "NL",
    "15701480": "ES",
    "15701488": "FR",
    "15701496": "PL",
    "15701504": "FR",
    "15701632": "DE",
    "15701696": "IT",
    "15701704": "ES",
    "15701708": "IT",
    "15701712": "NO",
    "15701716": "ES",
    "15701720": "SE",
    "15701724": "ES",
    "15701728": "FI",
    "15701736": "IT",
    "15701740": "AT",
    "15701744": "SE",
    "15701760": "FR",
    "15701776": "AT",
    "15701780": "CZ",
    "15701784": "DE",
    "15701792": "SE",
    "15701794": "US",
    "15701796": "DE",
    "15701798": "US",
    "15701800": "FR",
    "15701804": "DE",
    "15701808": "GB",
    "15701824": "DE",
    "15701828": "CZ",
    "15701832": "DK",
    "15701840": "FR",
    "15701856": "BE",
    "15701864": "DK",
    "15701868": "FR",
    "15701876": "ES",
    "15701888": "FR",
    "15701904": "BG",
    "15701912": "DE",
    "15701928": "GB",
    "15701944": "SK",
    "15701952": "DE",
    "15701968": "FR",
    "15701976": "DK",
    "15701992": "FR",
    "15702016": "DE",
    "15702064": "NL",
    "15702080": "DE",
    "15702120": "NO",
    "15702128": "FI",
    "15702144": "HR",
    "15702184": "AT",
    "15702208": "PL",
    "15702216": "SK",
    "15702224": "PL",
    "15702248": "ES",
    "15702256": "FR",
    "15702264": "ES",
    "15702272": "GB",
    "15702528": "FR",
    "15702624": "DE",
    "15702656": "FR",
    "15702728": "GB",
    "15702736": "IE",
    "15702744": "FR",
    "15702752": "RU",
    "15702756": "SE",
    "15702760": "UA",
    "15702768": "FR",
    "15702776": "RO",
    "15702784": "FR",
    "15703040": "DE",
    "15703168": "FR",
    "15703296": "SE",
    "15703552": "FR",
    "15703869": "NO",
    "15703872": "FR",
    "15703876": "NO",
    "15703880": "FR",
    "15703884": "NO",
    "15703888": "FR",
    "15703892": "NO",
    "15703896": "FR",
    "15703900": "NO",
    "15703904": "FR",
    "15703908": "NO",
    "15703910": "FR",
    "15704064": "BE",
    "15704186": "ES",
    "15704187": "BE",
    "15704283": "US",
    "15704284": "BE",
    "15705456": "SE",
    "15705464": "DE",
    "15705472": "BE",
    "15705552": "GB",
    "15705568": "BE",
    "15706483": "DE",
    "15706484": "BE",
    "15706632": "FR",
    "15706640": "BE",
    "15707148": "AT",
    "15707152": "BE",
    "15707648": "GB",
    "15707664": "BE",
    "15708032": "DE",
    "15708160": "GB",
    "15708416": "FR",
    "15708480": "SE",
    "15708512": "GB",
    "15708528": "FR",
    "15708676": "NL",
    "15708680": "FR",
    "15708688": "SE",
    "15708704": "FR",
    "15708928": "DE",
    "15708944": "HU",
    "15708952": "ES",
    "15708960": "PL",
    "15708992": "DE",
    "15709024": "FR",
    "15709040": "DE",
    "15709184": "FR",
    "15710728": "NL",
    "15710732": "PL",
    "15710736": "FR",
    "15710802": "DE",
    "15710803": "FR",
    "15710848": "DE",
    "15710880": "FR",
    "15710912": "NL",
    "15710920": "DE",
    "15710928": "SE",
    "15710944": "DE",
    "15710976": "IT",
    "15710980": "ES",
    "15710984": "FR",
    "15710992": "NL",
    "15711008": "DE",
    "15711072": "GB",
    "15711088": "DE",
    "15711104": "CH",
    "15711120": "DE",
    "15711136": "IS",
    "15711168": "DE",
    "15711176": "SE",
    "15711200": "DE",
    "15711216": "IT",
    "15711224": "DK",
    "15711232": "FR",
    "15711488": "DE",
    "15711632": "NL",
    "15711648": "DE",
    "15711676": "BE",
    "15711680": "GB",
    "15711712": "SE",
    "15711728": "ES",
    "15711744": "GB",
    "15712000": "DE",
    "15712256": "GB",
    "15712880": "US",
    "15712884": "GB",
    "15713536": "BE",
    "15713544": "GB",
    "15713584": "PL",
    "15713592": "ES",
    "15713600": "GB",
    "15713792": "HU",
    "15713808": "IE",
    "15713824": "SE",
    "15713840": "DE",
    "15713844": "SE",
    "15713848": "NO",
    "15713852": "FI",
    "15713856": "DE",
    "15713864": "BE",
    "15713872": "ES",
    "15713880": "SE",
    "15713888": "DK",
    "15713904": "DE",
    "15713920": "CH",
    "15713940": "HU",
    "15713944": "DE",
    "15713952": "NL",
    "15713960": "CH",
    "15713968": "GB",
    "15713976": "PL",
    "15713980": "DK",
    "15713984": "DE",
    "15714000": "FR",
    "15714016": "FI",
    "15714032": "DE",
    "15714048": "GB",
    "15714120": "BA",
    "15714128": "GB",
    "15714144": "FR",
    "15714176": "GB",
    "15714240": "DE",
    "15714272": "GB",
    "15714368": "MD",
    "15714376": "GB",
    "15714392": "DK",
    "15714400": "GB",
    "15714432": "CH",
    "15714440": "GB",
    "15714444": "IT",
    "15714448": "LU",
    "15714456": "FR",
    "15714472": "GB",
    "15714512": "LU",
    "15714516": "IT",
    "15714520": "GB",
    "15714544": "FR",
    "15714548": "PL",
    "15714552": "GB",
    "15714944": "SK",
    "15714952": "PL",
    "15714956": "DE",
    "15714960": "TR",
    "15714964": "AT",
    "15714968": "FR",
    "15714972": "BE",
    "15714976": "PL",
    "15714980": "IE",
    "15714984": "SE",
    "15714992": "NL",
    "15714996": "ES",
    "15715000": "GB",
    "15715004": "CZ",
    "15715008": "NL",
    "15715024": "FR",
    "15715028": "BE",
    "15715032": "HU",
    "15715036": "PT",
    "15715040": "GB",
    "15715044": "DE",
    "15715048": "IT",
    "15715052": "GB",
    "15715064": "PT",
    "15715068": "GB",
    "15716098": "DE",
    "15716099": "GB",
    "15716224": "DE",
    "15716608": "NO",
    "15716616": "PL",
    "15716680": "NL",
    "15716688": "PL",
    "15716752": "AT",
    "15716756": "FR",
    "15716772": "CZ",
    "15716776": "FR",
    "15716788": "HU",
    "15716792": "NL",
    "15716796": "IE",
    "15716800": "PL",
    "15716804": "NL",
    "15716808": "BE",
    "15716812": "FR",
    "15716820": "DE",
    "15716824": "FR",
    "15716832": "NL",
    "15716848": "FR",
    "15716864": "HU",
    "15716868": "BE",
    "15716872": "FR",
    "15716992": "IT",
    "15717032": "NL",
    "15717040": "IT",
    "15717056": "FR",
    "15717072": "CH",
    "15717080": "IT",
    "15717168": "PL",
    "15717176": "NL",
    "15717184": "BE",
    "15717192": "CH",
    "15717224": "NL",
    "15717232": "DE",
    "15717248": "BE",
    "15717252": "BG",
    "15717256": "ES",
    "15717288": "NL",
    "15717296": "CH",
    "15717304": "DE",
    "15717336": "PL",
    "15717344": "DE",
    "15717368": "ES",
    "15717376": "PL",
    "15717384": "DE",
    "15717392": "EE",
    "15717408": "SE",
    "15717424": "FR",
    "15717544": "IT",
    "15717560": "FR",
    "15717568": "GB",
    "15717584": "SE",
    "15717592": "IT",
    "15717608": "DE",
    "15717624": "PL",
    "15717632": "DE",
    "15717648": "PL",
    "15717656": "BE",
    "15717664": "DE",
    "15717760": "BE",
    "15717784": "GB",
    "15717788": "NL",
    "15717800": "FR",
    "15717808": "PL",
    "15717816": "HU",
    "15717824": "FR",
    "15717832": "CZ",
    "15717840": "NL",
    "15717844": "ES",
    "15717848": "DK",
    "15717864": "FR",
    "15717872": "ZA",
    "15717888": "DK",
    "15717920": "DE",
    "15717952": "NL",
    "15717960": "DE",
    "15717976": "IT",
    "15717984": "GB",
    "15717992": "NL",
    "15718000": "GB",
    "15718032": "FR",
    "15718036": "TR",
    "15718040": "SE",
    "15718048": "US",
    "15718052": "FR",
    "15718056": "DE",
    "15718064": "FI",
    "15718080": "PL",
    "15718144": "GB",
    "15718176": "RS",
    "15718184": "FI",
    "15718192": "LT",
    "15718200": "NL",
    "15718208": "GB",
    "15718232": "HR",
    "15718240": "GB",
    "15718304": "DE",
    "15718368": "FI",
    "15718376": "DE",
    "15718400": "PL",
    "15718456": "GB",
    "15718464": "NL",
    "15718480": "DE",
    "15718504": "SE",
    "15718512": "ES",
    "15718528": "GB",
    "15718592": "FR",
    "15718608": "CH",
    "15718616": "DE",
    "15718624": "FR",
    "15718640": "AT",
    "15718656": "SE",
    "15718784": "FR",
    "15718800": "ES",
    "15718804": "FR",
    "15718808": "DE",
    "15718816": "SE",
    "15718824": "GB",
    "15718848": "PL",
    "15718864": "NL",
    "15718880": "DE",
    "15719168": "GB",
    "15719192": "FR",
    "15719196": "GB",
    "15719200": "CH",
    "15719204": "GB",
    "15719224": "FI",
    "15719228": "GB",
    "15719232": "IT",
    "15719236": "GB",
    "15719244": "IT",
    "15719248": "PL",
    "15719256": "FR",
    "15719264": "RO",
    "15719272": "PL",
    "15719288": "GB",
    "15719320": "PL",
    "15719328": "GB",
    "15719352": "SE",
    "15719360": "FR",
    "15719392": "GB",
    "15719408": "FR",
    "15719424": "GB",
    "15719552": "DK",
    "15719560": "DE",
    "15719568": "BE",
    "15719600": "DE",
    "15719616": "GB",
    "15719628": "IT",
    "15719632": "GB",
    "15719648": "BE",
    "15719680": "GB",
    "15719808": "NL",
    "15719824": "GB",
    "15719840": "PL",
    "15719848": "LT",
    "15719856": "FR",
    "15719860": "DE",
    "15719872": "CZ",
    "15719936": "DE",
    "15720072": "BE",
    "15720080": "SE",
    "15720088": "PL",
    "15720092": "DE",
    "15720096": "FR",
    "15720104": "CH",
    "15720112": "BE",
    "15720128": "NL",
    "15720144": "GB",
    "15720192": "DE",
    "15720208": "GB",
    "15720264": "DE",
    "15720272": "GB",
    "15720296": "SE",
    "15720304": "GB",
    "15720320": "NL",
    "15720336": "IE",
    "15720344": "NL",
    "15720360": "FR",
    "15720368": "NL",
    "15720384": "IT",
    "15720392": "NL",
    "15720400": "IT",
    "15720404": "FR",
    "15720408": "NL",
    "15720448": "SE",
    "15720576": "DE",
    "15720608": "GB",
    "15720616": "ES",
    "15720620": "SE",
    "15721728": "FI",
    "15721732": "SE",
    "15721824": "IT",
    "15721856": "SE",
    "15721996": "FR",
    "15722000": "SE",
    "15722320": "CH",
    "15722328": "ES",
    "15722336": "SE",
    "15723008": "GR",
    "15723012": "SE",
    "15723072": "CH",
    "15723136": "SE",
    "15723965": "ES",
    "15723968": "SE",
    "15723996": "ES",
    "15724005": "SE",
    "15724006": "ES",
    "15724021": "SE",
    "15724022": "ES",
    "15724023": "SE",
    "15724024": "ES",
    "15724030": "SE",
    "15724544": "GB",
    "15725056": "DE",
    "15725312": "GB",
    "15725376": "NO",
    "15725384": "AT",
    "15725388": "NL",
    "15725392": "DK",
    "15725408": "NL",
    "15725440": "GB",
    "15725476": "DE",
    "15725504": "FR",
    "15725512": "DE",
    "15725516": "FR",
    "15725520": "GB",
    "15725524": "ES",
    "15725528": "PL",
    "15725532": "SE",
    "15725536": "NL",
    "15725544": "DE",
    "15725552": "GB",
    "15725560": "DE",
    "15725824": "IT",
    "15725832": "PL",
    "15725840": "SE",
    "15726080": "DE",
    "15726088": "SE",
    "15726104": "FR",
    "15726112": "GB",
    "15726120": "SE",
    "15726136": "ES",
    "15726144": "SE",
    "15726160": "FR",
    "15726168": "SE",
    "15726200": "DE",
    "15726208": "SE",
    "15726256": "DE",
    "15726264": "SE",
    "15726466": "DK",
    "15726470": "SE",
    "15726474": "DK",
    "15726478": "SE",
    "15726482": "DK",
    "15726486": "SE",
    "15726516": "DK",
    "15726520": "SE",
    "15726524": "DK",
    "15726528": "SE",
    "15726532": "DK",
    "15726536": "SE",
    "15726540": "DK",
    "15726544": "SE",
    "15726548": "DK",
    "15726552": "SE",
    "15726556": "DK",
    "15726560": "SE",
    "15728640": "LT",
    "15732736": "DE",
    "15736832": "RU",
    "15745024": "SA",
    "15749120": "GB",
    "15753216": "HK",
    "15753472": "LU",
    "15753728": "FR",
    "15754240": "RU",
    "15754496": "ZA",
    "15754752": "RU",
    "15755008": "US",
    "15755264": "NL",
    "15755520": "LU",
    "15755776": "CY",
    "15756032": "FR",
    "15756288": "GB",
    "15756800": "RU",
    "15757056": "US",
    "15757312": "LU",
    "15757568": "SE",
    "15757824": "LU",
    "15758080": "FR",
    "15758336": "AU",
    "15760384": "BR",
    "15760640": "DK",
    "15760896": "ES",
    "15761408": "NL",
    "15765504": "RS",
    "15769600": "FR",
    "15777792": "KE",
    "15781888": "RU",
    "15785984": "AT",
    "15790080": "RU",
    "15794176": "KZ",
    "15798272": "AT",
    "15802368": "KZ",
    "15806464": "GB",
    "15808512": "DE",
    "15810560": "US",
    "15811553": "NO",
    "15811554": "US",
    "15811562": "NO",
    "15811563": "US",
    "15811665": "GB",
    "15811667": "US",
    "15812017": "GB",
    "15812018": "US",
    "15812463": "FR",
    "15812464": "US",
    "15812944": "GB",
    "15812960": "US",
    "15814656": "NO",
    "15818752": "CH",
    "15822848": "LI",
    "15826944": "PL",
    "15828992": "IT",
    "15831040": "BH",
    "15835136": "US",
    "15839232": "GE",
    "15843328": "DE",
    "15847424": "FR",
    "15851520": "IT",
    "15855616": "GE",
    "15859712": "IR",
    "15863808": "FI",
    "15867904": "SK",
    "15872000": "RU",
    "15874048": "NL",
    "15874304": "RU",
    "15874560": "NL",
    "15874816": "RU",
    "15875584": "DE",
    "15875840": "SE",
    "15876096": "RU",
    "15888384": "BA",
    "15892480": "DE",
    "15908864": "CH",
    "15912960": "KZ",
    "15917056": "NL",
    "15925248": "RU",
    "15929344": "US",
    "15933440": "DE",
    "15941632": "RU",
    "15945728": "PT",
    "15949824": "CZ",
    "15953920": "DK",
    "15955456": "GB",
    "15955968": "DK",
    "15958016": "US",
    "15959040": "RU",
    "15961600": "US",
    "15962112": "UA",
    "15966208": "AT",
    "15970304": "GB",
    "15974400": "DE",
    "15978496": "CH",
    "15982592": "DE",
    "15983616": "SK",
    "15983872": "AU",
    "15984128": "CA",
    "15984640": "RS",
    "15985664": "CZ",
    "15986688": "MQ",
    "15988736": "GP",
    "15990784": "RU",
    "15991040": "FR",
    "15991296": "ES",
    "15991552": "DE",
    "15991808": "IT",
    "15992064": "RU",
    "15992320": "IT",
    "15992576": "IR",
    "15992832": "GB",
    "15993088": "SE",
    "15993344": "PT",
    "15993600": "IR",
    "15993856": "LT",
    "15994112": "DE",
    "15994624": "GB",
    "15994880": "CY",
    "15998976": "RU",
    "16003072": "ES",
    "16007168": "SE",
    "16015360": "HU",
    "16019456": "IT",
    "16023552": "PL",
    "16031744": "IL",
    "16035840": "GB",
    "16039936": "SE",
    "16044032": "DE",
    "16048128": "RU",
    "16052224": "DE",
    "16056320": "ES",
    "16060416": "FR",
    "16064528": "BE",
    "16064544": "FR",
    "16064640": "DE",
    "16064648": "FR",
    "16066816": "US",
    "16067008": "FR",
    "16067584": "GB",
    "16068096": "FR",
    "16068352": "TR",
    "16068608": "FR",
    "16072704": "DE",
    "16076800": "MD",
    "16080896": "RS",
    "16081920": "DK",
    "16082944": "DE",
    "16084992": "UA",
    "16089088": "DE",
    "16097280": "GR",
    "16101376": "PL",
    "16105472": "AT",
    "16109568": "MT",
    "16113664": "SE",
    "16117760": "RU",
    "16121856": "DZ",
    "16125952": "RU",
    "16129024": "AL",
    "16129280": "IN",
    "16129536": "NL",
    "16129792": "LV",
    "16130048": "DE",
    "16134144": "FR",
    "16136960": "DE",
    "16137472": "FR",
    "16137728": "DE",
    "16138240": "RU",
    "16146432": "LU",
    "16150528": "DE",
    "16154624": "IL",
    "16158720": "FI",
    "16166912": "NL",
    "16175104": "RU",
    "16179200": "SI",
    "16179712": "MY",
    "16179968": "BR",
    "16180224": "SI",
    "16180736": "VN",
    "16180992": "HK",
    "16181248": "DE",
    "16183296": "RU",
    "16187392": "FR",
    "16191488": "GB",
    "16195584": "RU",
    "16199680": "GB",
    "16201728": "NL",
    "16201792": "IE",
    "16201856": "GB",
    "16203776": "IT",
    "16207872": "GB",
    "16211968": "RU",
    "16220160": "US",
    "16222464": "GB",
    "16222483": "NG",
    "16222484": "GB",
    "16222720": "US",
    "16224000": "KE",
    "16224256": "US",
    "16225024": "TZ",
    "16225280": "US",
    "16226304": "DE",
    "16226560": "US",
    "16228352": "NL",
    "16232448": "RU",
    "16236544": "NL",
    "16244736": "FR",
    "16248832": "FI",
    "16252928": "NG",
    "16257024": "IS",
    "16261120": "NL",
    "16265216": "RU",
    "16269312": "TG",
    "16273408": "RU",
    "16277504": "FI",
    "16285696": "SE",
    "16289792": "RU",
    "16293888": "FI",
    "16297984": "GB",
    "16302080": "LI",
    "16303360": "CH",
    "16303488": "LI",
    "16303636": "CH",
    "16303637": "LI",
    "16306176": "FR",
    "16310272": "SE",
    "16314368": "FI",
    "16318464": "AU",
    "16322560": "GB",
    "16326656": "IT",
    "16330752": "GB",
    "16334848": "DZ",
    "16338944": "BY",
    "16343040": "GB",
    "16347136": "IR",
    "16348160": "DE",
    "16349184": "AT",
    "16350208": "IT",
    "16351232": "GB",
    "16351488": "RU",
    "16351744": "PL",
    "16352000": "RU",
    "16352256": "NL",
    "16352512": "CZ",
    "16352768": "US",
    "16353024": "RU",
    "16353536": "KZ",
    "16355328": "RU",
    "16357376": "KZ",
    "16359424": "HU",
    "16363520": "RU",
    "16371712": "NL",
    "16373760": "GB",
    "16375808": "UA",
    "16379904": "IE",
    "16384000": "CZ",
    "16392192": "MA",
    "16396288": "LV",
    "16400384": "RU",
    "16408576": "GB",
    "16412672": "EE",
    "16416768": "DE",
    "16420864": "IL",
    "16424960": "RU",
    "16433152": "IR",
    "16437248": "RU",
    "16445440": "SK",
    "16449536": "GB",
    "16457728": "TR",
    "16461824": "RU",
    "16465920": "ES",
    "16470016": "DE",
    "16474112": "FR",
    "16477184": "BE",
    "16478208": "RU",
    "16488704": "NL",
    "16488960": "RU",
    "16490496": "PT",
    "16490700": "ES",
    "16490704": "PT",
    "16490976": "DE",
    "16490984": "PT",
    "16491832": "ES",
    "16491836": "PT",
    "16492056": "ES",
    "16492064": "PT",
    "16492336": "ES",
    "16492344": "PT",
    "16492960": "ES",
    "16492992": "PT",
    "16493976": "ES",
    "16493980": "PT",
    "16494656": "ES",
    "16494664": "PT",
    "16495104": "ES",
    "16495368": "GB",
    "16495376": "ES",
    "16495616": "IT",
    "16496128": "DE",
    "16496152": "ES",
    "16496156": "DE",
    "16496640": "PT",
    "16496896": "ES",
    "16497152": "GB",
    "16497172": "PT",
    "16497180": "GB",
    "16497196": "PT",
    "16497204": "GB",
    "16497212": "PT",
    "16497216": "GB",
    "16497220": "PT",
    "16497224": "GB",
    "16497232": "PT",
    "16497240": "GB",
    "16497248": "PT",
    "16497268": "GB",
    "16497280": "PT",
    "16497284": "GB",
    "16497288": "PT",
    "16497300": "GB",
    "16497304": "PT",
    "16497316": "GB",
    "16497320": "PT",
    "16497330": "GB",
    "16497348": "PT",
    "16497352": "GB",
    "16497356": "PT",
    "16497360": "GB",
    "16497364": "PT",
    "16497368": "GB",
    "16497372": "PT",
    "16497380": "GB",
    "16497384": "PT",
    "16497392": "GB",
    "16497408": "PT",
    "16497444": "ES",
    "16497448": "PT",
    "16497472": "ES",
    "16497476": "PT",
    "16497496": "ES",
    "16497500": "PT",
    "16497524": "ES",
    "16497528": "PT",
    "16497568": "ES",
    "16497572": "PT",
    "16497664": "ES",
    "16497680": "PT",
    "16497684": "ES",
    "16497692": "PT",
    "16497700": "ES",
    "16497728": "PT",
    "16497732": "ES",
    "16497752": "PT",
    "16497760": "ES",
    "16497772": "PT",
    "16497776": "ES",
    "16497784": "PT",
    "16497804": "ES",
    "16497808": "PT",
    "16497812": "ES",
    "16497832": "PT",
    "16497836": "ES",
    "16497840": "PT",
    "16497848": "ES",
    "16497860": "PT",
    "16497868": "ES",
    "16497872": "PT",
    "16497876": "ES",
    "16497880": "PT",
    "16497884": "ES",
    "16497896": "PT",
    "16497900": "ES",
    "16497904": "PT",
    "16497908": "ES",
    "16497912": "PT",
    "16497916": "ES",
    "16497920": "IT",
    "16497924": "PT",
    "16497932": "IT",
    "16497936": "PT",
    "16497940": "IT",
    "16497972": "PT",
    "16497976": "IT",
    "16498004": "PT",
    "16498008": "ES",
    "16498012": "IT",
    "16498024": "PT",
    "16498028": "IT",
    "16498032": "PT",
    "16498036": "IT",
    "16498040": "PT",
    "16498044": "IT",
    "16498048": "PT",
    "16498056": "IT",
    "16498072": "PT",
    "16498080": "IT",
    "16498116": "PT",
    "16498120": "IT",
    "16498124": "PT",
    "16498128": "IT",
    "16498132": "PT",
    "16498136": "IT",
    "16498152": "PT",
    "16498160": "IT",
    "16498176": "ES",
    "16498688": "DK",
    "16499456": "SE",
    "16499712": "DK",
    "16500736": "SE",
    "16500992": "DK",
    "16502784": "US",
    "16506880": "RU",
    "16510976": "CZ",
    "16515072": "PL",
    "16519168": "RU",
    "16523264": "AT",
    "16527360": "HU",
    "16531456": "GB",
    "16535552": "NL",
    "16539648": "DE",
    "16543744": "GB",
    "16547840": "RU",
    "16556032": "SE",
    "16556724": "NO",
    "16556728": "SE",
    "16556844": "DE",
    "16556848": "SE",
    "16557064": "NL",
    "16557068": "SE",
    "16557436": "US",
    "16557440": "SE",
    "16557448": "BE",
    "16557452": "SE",
    "16557696": "NL",
    "16557700": "SE",
    "16557860": "NL",
    "16557864": "SE",
    "16558040": "DE",
    "16558048": "SE",
    "16558432": "FR",
    "16558436": "SE",
    "16558464": "FR",
    "16558472": "SE",
    "16559648": "NL",
    "16559664": "SE",
    "16560104": "NL",
    "16560108": "SE",
    "16560824": "FR",
    "16560832": "SE",
    "16561024": "FR",
    "16561028": "SE",
    "16561152": "NL",
    "16561168": "SE",
    "16561856": "NL",
    "16561872": "SE",
    "16562224": "FR",
    "16562240": "SE",
    "16562820": "MY",
    "16562824": "SE",
    "16562880": "FR",
    "16562896": "SE",
    "16563056": "GB",
    "16563072": "SE",
    "16563392": "PL",
    "16563396": "BG",
    "16563400": "BR",
    "16563404": "TR",
    "16563408": "SE",
    "16563604": "NL",
    "16563608": "SE",
    "16563648": "DK",
    "16563664": "SE",
    "16564224": "IT",
    "16568320": "SE",
    "16572416": "IT",
    "16576512": "UA",
    "16580608": "RU",
    "16588800": "IT",
    "16592896": "BG",
    "16596992": "ES",
    "16601088": "CH",
    "16605184": "BE",
    "16605200": "FI",
    "16605216": "SE",
    "16605224": "IT",
    "16605232": "LU",
    "16605240": "RO",
    "16605256": "PL",
    "16605288": "IT",
    "16605296": "BG",
    "16605304": "SK",
    "16605312": "SI",
    "16605320": "SE",
    "16605336": "RO",
    "16605344": "CH",
    "16605352": "HU",
    "16605360": "RO",
    "16605368": "ES",
    "16605376": "BE",
    "16605384": "HU",
    "16605392": "DE",
    "16605400": "SE",
    "16605408": "HR",
    "16605416": "SE",
    "16605424": "RS",
    "16605440": "RO",
    "16605448": "BG",
    "16605452": "FI",
    "16605456": "PT",
    "16605464": "ES",
    "16605472": "BE",
    "16605480": "ES",
    "16605496": "SE",
    "16605504": "LU",
    "16605508": "ES",
    "16605512": "SE",
    "16605528": "ES",
    "16605544": "NO",
    "16605552": "IT",
    "16605560": "SE",
    "16605576": "ES",
    "16605584": "SE",
    "16605616": "ES",
    "16605632": "SE",
    "16605648": "BE",
    "16605664": "IT",
    "16605672": "SE",
    "16605680": "BE",
    "16605688": "IT",
    "16605696": "FR",
    "16605952": "SE",
    "16606208": "DE",
    "16606224": "PL",
    "16606232": "DE",
    "16606272": "CZ",
    "16606280": "DE",
    "16606456": "US",
    "16606472": "DE",
    "16606496": "DK",
    "16606504": "DE",
    "16606516": "LU",
    "16606520": "DE",
    "16606632": "DK",
    "16606640": "DE",
    "16606656": "CZ",
    "16606664": "DE",
    "16606680": "CZ",
    "16606688": "DE",
    "16606768": "LU",
    "16606776": "DE",
    "16606848": "LU",
    "16606864": "DE",
    "16606896": "CZ",
    "16606904": "DE",
    "16607064": "LU",
    "16607072": "CZ",
    "16607080": "DE",
    "16607232": "GB",
    "16607432": "IN",
    "16607440": "GB",
    "16608256": "NL",
    "16608272": "FR",
    "16608280": "NL",
    "16608768": "GB",
    "16609024": "FR",
    "16609280": "NL",
    "16609536": "GB",
    "16609792": "DE",
    "16610008": "LU",
    "16610016": "DE",
    "16610048": "IE",
    "16610304": "LT",
    "16610312": "IE",
    "16610320": "IT",
    "16610328": "SE",
    "16610336": "BE",
    "16610344": "SE",
    "16610352": "DK",
    "16610368": "BE",
    "16610372": "CH",
    "16610380": "BE",
    "16610384": "DK",
    "16610400": "SE",
    "16610408": "IT",
    "16610416": "DK",
    "16610424": "IT",
    "16610432": "RO",
    "16610440": "IE",
    "16610448": "BE",
    "16610452": "CH",
    "16610460": "BE",
    "16610472": "CH",
    "16610480": "AT",
    "16610488": "CZ",
    "16610504": "SE",
    "16610512": "DK",
    "16610516": "RO",
    "16610520": "DK",
    "16610528": "BE",
    "16610532": "DK",
    "16610536": "NO",
    "16610544": "DK",
    "16610560": "PL",
    "16610584": "BE",
    "16610592": "CH",
    "16610596": "LU",
    "16610600": "BE",
    "16610608": "IT",
    "16610616": "PL",
    "16610624": "BE",
    "16610632": "FR",
    "16610636": "BE",
    "16610640": "NL",
    "16610648": "BE",
    "16610656": "ES",
    "16610660": "DK",
    "16610672": "HU",
    "16610680": "DK",
    "16610688": "SE",
    "16610692": "DK",
    "16610720": "CZ",
    "16610728": "BE",
    "16610732": "IE",
    "16610736": "ES",
    "16610744": "DK",
    "16610760": "SE",
    "16610768": "BE",
    "16610772": "IT",
    "16610780": "BE",
    "16610800": "CZ",
    "16610832": "IT",
    "16610848": "ES",
    "16610864": "CZ",
    "16610872": "RO",
    "16610888": "CH",
    "16610896": "IT",
    "16610904": "PL",
    "16610912": "ES",
    "16610928": "BE",
    "16610936": "ES",
    "16610952": "FR",
    "16610960": "BE",
    "16610968": "BG",
    "16610976": "BE",
    "16610992": "PL",
    "16611000": "BE",
    "16611004": "IT",
    "16611024": "AT",
    "16611032": "IT",
    "16611064": "BE",
    "16611072": "CZ",
    "16611076": "SK",
    "16611080": "ES",
    "16611084": "BE",
    "16611088": "LU",
    "16611096": "NO",
    "16611112": "BE",
    "16611120": "ES",
    "16611124": "PL",
    "16611136": "IT",
    "16611152": "HR",
    "16611168": "IT",
    "16611184": "BE",
    "16611188": "LU",
    "16611192": "HU",
    "16611208": "LU",
    "16611212": "SE",
    "16611216": "BE",
    "16611232": "PL",
    "16611248": "DK",
    "16611264": "ES",
    "16611280": "DK",
    "16611288": "BE",
    "16611296": "IT",
    "16611312": "DK",
    "16611320": "BE",
    "16611328": "ES",
    "16611336": "SE",
    "16611344": "BE",
    "16611360": "PL",
    "16611368": "SE",
    "16611376": "IT",
    "16611384": "PL",
    "16611392": "IT",
    "16611400": "BE",
    "16611408": "IT",
    "16611416": "BE",
    "16611424": "TR",
    "16611432": "ES",
    "16611436": "PL",
    "16611440": "BE",
    "16611456": "IT",
    "16611460": "ES",
    "16611464": "SE",
    "16611488": "ES",
    "16611520": "LT",
    "16611528": "IT",
    "16611536": "PL",
    "16611544": "ES",
    "16611560": "FR",
    "16611564": "IT",
    "16611568": "RO",
    "16611576": "LV",
    "16611584": "IT",
    "16611588": "ES",
    "16611592": "LV",
    "16611600": "IT",
    "16611608": "ES",
    "16611640": "HU",
    "16611648": "ES",
    "16611652": "IE",
    "16611656": "PL",
    "16611664": "RO",
    "16611672": "MD",
    "16611680": "PL",
    "16611704": "BE",
    "16611720": "PT",
    "16611728": "ES",
    "16611736": "BE",
    "16611744": "IT",
    "16611756": "BE",
    "16611768": "PL",
    "16611776": "HU",
    "16611784": "BE",
    "16611800": "FR",
    "16611804": "PL",
    "16611812": "FR",
    "16611816": "AT",
    "16611824": "BE",
    "16611828": "PL",
    "16611840": "FR",
    "16612096": "GB",
    "16612352": "FR",
    "16613376": "IR",
    "16621568": "HR",
    "16625664": "SA",
    "16629760": "FR",
    "16633856": "DE",
    "16634880": "NL",
    "16635136": "DE",
    "16635144": "PL",
    "16635148": "DE",
    "16637952": "RU",
    "16642048": "TR",
    "16644096": "NL",
    "16644352": "DE",
    "16644608": "US",
    "16644864": "DE",
    "16645120": "US",
    "16645632": "TR",
    "16646144": "UA",
    "16650240": "RU",
    "16654336": "NO",
    "16658432": "RU",
    "16662528": "CH",
    "16666624": "MT",
    "16670720": "RU",
    "16678912": "DE",
    "16683008": "US",
    "16687104": "CH",
    "16695296": "IT",
    "16699392": "CA",
    "16700416": "US",
    "16700928": "DE",
    "16701440": "CA",
    "16702464": "US",
    "16703488": "ES",
    "16704512": "SE",
    "16705536": "CZ",
    "16707584": "SE",
    "16711680": "DE",
    "16713120": "SE",
    "16713152": "DE",
    "16713200": "US",
    "16713208": "DE",
    "16713536": "CH",
    "16713552": "DE",
    "16714880": "CH",
    "16714896": "DE",
    "16715776": "RU",
    "16719872": "GB",
    "16722432": "DE",
    "16722688": "KE",
    "16722944": "GB",
    "16723716": "DE",
    "16723717": "GB",
    "16726528": "US",
    "16726784": "GB",
    "16728064": "UA",
    "16732160": "RU",
    "16736256": "CH",
    "16740352": "ES",
    "16744448": "RU",
    "16752640": "LU",
    "16756736": "RU",
    "16760832": "GB",
    "16769024": "ES",
    "16773120": "NL"
}